<?xml version="1.0" encoding="UTF-8"?><labels locale="fr">
<label key="1879049792" value="Pays de Bree"/>
<label key="1879049816" value="Eriador"/>
<label key="1879051236" value="Gorothlad"/>
<label key="1879051583" value="La Comté"/>
<label key="1879051861" value="Les Landes d'Etten"/>
<label key="1879061048" value="Ered Luin"/>
<label key="1879062345" value="Les Terres Solitaires"/>
<label key="1879063884" value="Angmar"/>
<label key="1879063917" value="Seamia Est"/>
<label key="1879063918" value="Seamia Ouest"/>
<label key="1879063919" value="FIX ME: Unassigned"/>
<label key="1879063920" value="Test"/>
<label key="1879063921" value="Val de Thrain"/>
<label key="1879063922" value="Basses-Terres"/>
<label key="1879063923" value="Haudh Lin"/>
<label key="1879063924" value="Falathlorn"/>
<label key="1879063925" value="Sarnur"/>
<label key="1879063926" value="Rath Teraig"/>
<label key="1879063927" value="Refuge d'Edhelion"/>
<label key="1879063928" value="Falathlorn"/>
<label key="1879063929" value="Celondim"/>
<label key="1879063930" value="Vignoble de Limael"/>
<label key="1879063931" value="Kheledûl"/>
<label key="1879063932" value="Porte de Thorin"/>
<label key="1879063933" value="Sud de la Trouée des Trolls"/>
<label key="1879063934" value="Nord de la Trouée des Trolls"/>
<label key="1879063935" value="Gorges du Bruinen"/>
<label key="1879063936" value="Haute Lande"/>
<label key="1879063937" value="Nan Tornaeth"/>
<label key="1879063938" value="Val des Géants"/>
<label key="1879063939" value="Vallée de Fondcombe"/>
<label key="1879063940" value="Monts Brumeux"/>
<label key="1879063941" value="Source du Bruinen ouest"/>
<label key="1879063942" value="Source du Bruinen nord"/>
<label key="1879063943" value="Source du Bruinen est"/>
<label key="1879063944" value="Hautes Falaises"/>
<label key="1879063945" value="Monts des Géants"/>
<label key="1879063946" value="Helegrod"/>
<label key="1879063947" value="Annunlos"/>
<label key="1879063948" value="Collines Venteuses"/>
<label key="1879063949" value="Nain Enidh"/>
<label key="1879063950" value="Talath Gaun"/>
<label key="1879063951" value="Harloeg"/>
<label key="1879063952" value="Agamaur"/>
<label key="1879063953" value="Haragmar"/>
<label key="1879063954" value="Talath Gaun"/>
<label key="1879063955" value="Garth Agarwen"/>
<label key="1879063956" value="Minas Eriol"/>
<label key="1879063957" value="Ram Duath"/>
<label key="1879063958" value="Collines Ouest"/>
<label key="1879063959" value="Malenhad Ouest"/>
<label key="1879063960" value="Collines au Blanc-Chapeau"/>
<label key="1879063961" value="Carn Dûm"/>
<label key="1879063962" value="Fasach-falroid"/>
<label key="1879063963" value="Fasach-larran"/>
<label key="1879063964" value="Malenhad Est"/>
<label key="1879063965" value="Imlad Balchorth"/>
<label key="1879063966" value="Himbar"/>
<label key="1879063967" value="Nan Gurth"/>
<label key="1879063968" value="Urugarth"/>
<label key="1879063969" value="Duvuinen"/>
<label key="1879063970" value="Maethad"/>
<label key="1879063971" value="Rhunendin"/>
<label key="1879063972" value="Pont-à-Tréteaux"/>
<label key="1879063973" value="Chemin Vert"/>
<label key="1879063974" value="Champs de Fornost"/>
<label key="1879063975" value="Nan Wathren"/>
<label key="1879063976" value="Chaussée des Morts"/>
<label key="1879063977" value="Nan Amlug ouest"/>
<label key="1879063978" value="Lande du Roi"/>
<label key="1879063979" value="Meluinen"/>
<label key="1879063980" value="Nan Amlug est"/>
<label key="1879063981" value="Rhunenlad"/>
<label key="1879063982" value="Dol Dinen"/>
<label key="1879063983" value="Annundir"/>
<label key="1879063984" value="Gosgenethad"/>
<label key="1879063985" value="Barad Gost"/>
<label key="1879063986" value="Fornost"/>
<label key="1879063987" value="Esteldin"/>
<label key="1879063988" value="Taur Gonwaith"/>
<label key="1879063989" value="Valgivre"/>
<label key="1879063990" value="Muraille d'Arador"/>
<label key="1879063991" value="Marches de Gram"/>
<label key="1879063992" value="Monts Froids"/>
<label key="1879063993" value="Hithlad"/>
<label key="1879063994" value="Pays de Bouc"/>
<label key="1879063995" value="Champs de Bree Nord"/>
<label key="1879063996" value="Vieille Forêt"/>
<label key="1879063997" value="Bois de Chet"/>
<label key="1879063998" value="Hauts des Galgals Nord"/>
<label key="1879063999" value="Hauts des Galgals Sud"/>
<label key="1879064000" value="Marais de l’Eau-aux-Cousins"/>
<label key="1879064001" value="Andrath"/>
<label key="1879064002" value="Collines de Brande"/>
<label key="1879064003" value="Les Bois de Brande"/>
<label key="1879064004" value="Lac de Simplétoile"/>
<label key="1879064005" value="Les Mornecrêtes"/>
<label key="1879064006" value="Champs de Bree Est"/>
<label key="1879064007" value="Bout du Bois de Chet"/>
<label key="1879064008" value="Ferme d'Anstacier"/>
<label key="1879064009" value="Les Champs-aux-Chevaux"/>
<label key="1879064010" value="Nen Harn"/>
<label key="1879064011" value="Collines Venteuses"/>
<label key="1879064012" value="Combe"/>
<label key="1879064013" value="Staddel"/>
<label key="1879064014" value="Archet"/>
<label key="1879064015" value="Bree"/>
<label key="1879064016" value="Champs de Grand'Cave"/>
<label key="1879064017" value="Hobbitebourg-Lèzeau"/>
<label key="1879064018" value="Pays de Touque"/>
<label key="1879064019" value="Le Maresque"/>
<label key="1879064020" value="Pays des Collines Vertes"/>
<label key="1879064021" value="Marais de Rushock"/>
<label key="1879064022" value="Forêt de Bindbole"/>
<label key="1879064023" value="Champs Verts"/>
<label key="1879064024" value="Champs du pont"/>
<label key="1879064025" value="Le Maresque"/>
<label key="1879064026" value="La Colline"/>
<label key="1879064027" value="Champ-du-Pont nord"/>
<label key="1879072154" value="Les Hauts du Nord"/>
<label key="1879072227" value="Les Monts Brumeux"/>
<label key="1879072246" value="La Trouée des Trolls"/>
<label key="1879075973" value="Raid des Monts Brumeux"/>
<label key="1879075991" value="Seamia"/>
<label key="1879078401" value="Champs de Bree Sud"/>
<label key="1879086544" value="Barandalf"/>
<label key="1879086545" value="Evendim"/>
<label key="1879086546" value="Annuminas"/>
<label key="1879086547" value="Men Erain"/>
<label key="1879086548" value="Tyl Annûn"/>
<label key="1879086549" value="Lac Evendim"/>
<label key="1879086550" value="Tyl Ruinen"/>
<label key="1879086551" value="Emyn Uial Sud"/>
<label key="1879086552" value="Tyrn Fornech"/>
<label key="1879086553" value="Parth Aduial"/>
<label key="1879086554" value="Emyn Uial Nord"/>
<label key="1879086555" value="Lopin du Taureau Mugissant"/>
<label key="1879086556" value="Tyl Aegonn"/>
<label key="1879093998" value="La Faille de Nûrz Ghâshu"/>
<label key="1879094891" value="Tâl Bruinen"/>
<label key="1879094892" value="Haut Col Nord"/>
<label key="1879094893" value="Haut Col Sud"/>
<label key="1879094894" value="Gobelinville"/>
<label key="1879098354" value="Résidences du Palais de Thorin"/>
<label key="1879098736" value="Résidences de Falathlorn"/>
<label key="1879098737" value="Résidences de la Comté"/>
<label key="1879098738" value="Résidences du Pays de Bree"/>
<label key="1879099191" value="La Caverne de Fror"/>
</labels>
