<?xml version="1.0" encoding="UTF-8"?><index key="1879064018">
<marker id="360513536"/>
<marker id="360513537"/>
<marker id="360513538"/>
<marker id="360513539"/>
<marker id="360513540"/>
<marker id="360513541"/>
<marker id="360513542"/>
<marker id="360513543"/>
<marker id="360513544"/>
<marker id="360513545"/>
<marker id="360513546"/>
<marker id="360513547"/>
<marker id="360513548"/>
<marker id="360513549"/>
<marker id="360513550"/>
<marker id="360513551"/>
<marker id="360513552"/>
<marker id="360513553"/>
<marker id="360513554"/>
<marker id="360513555"/>
<marker id="360513556"/>
<marker id="360513557"/>
<marker id="360513558"/>
<marker id="360513559"/>
<marker id="360513560"/>
<marker id="360513561"/>
<marker id="360513562"/>
<marker id="360513563"/>
<marker id="360513564"/>
<marker id="360513565"/>
<marker id="360513566"/>
<marker id="360513567"/>
<marker id="360513568"/>
<marker id="360513569"/>
<marker id="360513570"/>
<marker id="360513571"/>
<marker id="360513572"/>
<marker id="360513573"/>
<marker id="360513574"/>
<marker id="360513575"/>
<marker id="360513576"/>
<marker id="360513577"/>
<marker id="360513578"/>
<marker id="360513579"/>
<marker id="360513580"/>
<marker id="360513581"/>
<marker id="360513582"/>
<marker id="360513583"/>
<marker id="360513584"/>
<marker id="360513585"/>
<marker id="360513586"/>
<marker id="360513587"/>
<marker id="360513588"/>
<marker id="360513589"/>
<marker id="360513590"/>
<marker id="360513591"/>
<marker id="360513592"/>
<marker id="360513593"/>
<marker id="360513594"/>
<marker id="360513595"/>
<marker id="360513596"/>
<marker id="360513597"/>
<marker id="360513598"/>
<marker id="360513599"/>
<marker id="360513600"/>
<marker id="360513601"/>
<marker id="360513602"/>
<marker id="360513603"/>
<marker id="360513604"/>
<marker id="360513605"/>
<marker id="360513606"/>
<marker id="360513607"/>
<marker id="360513608"/>
<marker id="360513609"/>
<marker id="360513610"/>
<marker id="360513611"/>
<marker id="360513612"/>
<marker id="360513613"/>
<marker id="360513614"/>
<marker id="360513615"/>
<marker id="360513616"/>
<marker id="360513617"/>
<marker id="360513618"/>
<marker id="360513619"/>
<marker id="360513620"/>
<marker id="360513621"/>
<marker id="360513622"/>
<marker id="360513623"/>
<marker id="360513624"/>
<marker id="360513625"/>
<marker id="360513626"/>
<marker id="360513627"/>
<marker id="360513628"/>
<marker id="360513629"/>
<marker id="360513630"/>
<marker id="360513631"/>
<marker id="360513632"/>
<marker id="360513633"/>
<marker id="360513634"/>
<marker id="360513635"/>
<marker id="360513636"/>
<marker id="360513637"/>
<marker id="360513638"/>
<marker id="360513639"/>
<marker id="360513640"/>
<marker id="360513641"/>
<marker id="360513642"/>
<marker id="360513643"/>
<marker id="360513644"/>
<marker id="360513645"/>
<marker id="360513646"/>
<marker id="360513647"/>
<marker id="360513648"/>
<marker id="360513649"/>
<marker id="360513650"/>
<marker id="360513651"/>
<marker id="360513652"/>
<marker id="360513653"/>
<marker id="360513654"/>
<marker id="360513655"/>
<marker id="360513656"/>
<marker id="360513657"/>
<marker id="360513658"/>
<marker id="360513659"/>
<marker id="360513660"/>
<marker id="360513661"/>
<marker id="360513662"/>
<marker id="360513663"/>
<marker id="360513664"/>
<marker id="360513665"/>
<marker id="360513666"/>
<marker id="360513667"/>
<marker id="360513668"/>
<marker id="360513669"/>
<marker id="360513670"/>
<marker id="360513671"/>
<marker id="360513672"/>
<marker id="360513673"/>
<marker id="360513674"/>
<marker id="360513675"/>
<marker id="360513676"/>
<marker id="360513677"/>
<marker id="360513678"/>
<marker id="360513679"/>
<marker id="360513680"/>
<marker id="360513681"/>
<marker id="360513682"/>
<marker id="360513683"/>
<marker id="360513684"/>
<marker id="360513685"/>
<marker id="360513686"/>
<marker id="360513687"/>
<marker id="360513688"/>
<marker id="360513689"/>
<marker id="360513690"/>
<marker id="360513691"/>
<marker id="360513692"/>
<marker id="360513693"/>
<marker id="360513694"/>
<marker id="360513695"/>
<marker id="360513696"/>
<marker id="360513697"/>
<marker id="360513698"/>
<marker id="360513699"/>
<marker id="360513700"/>
<marker id="360513701"/>
<marker id="360513702"/>
<marker id="360513703"/>
<marker id="360513704"/>
<marker id="360513705"/>
<marker id="360513706"/>
<marker id="360513707"/>
<marker id="360513708"/>
<marker id="360513709"/>
<marker id="360513710"/>
<marker id="360513711"/>
<marker id="360513712"/>
<marker id="360513713"/>
<marker id="360513714"/>
<marker id="360513715"/>
<marker id="360513716"/>
<marker id="360513717"/>
<marker id="360513718"/>
<marker id="360513719"/>
<marker id="360513720"/>
<marker id="360513721"/>
<marker id="360513722"/>
<marker id="360513723"/>
<marker id="360513724"/>
<marker id="360513725"/>
<marker id="360513726"/>
<marker id="360513727"/>
<marker id="360513728"/>
<marker id="360513729"/>
<marker id="360513730"/>
<marker id="360513731"/>
<marker id="360513732"/>
<marker id="360513733"/>
<marker id="360513734"/>
<marker id="360513735"/>
<marker id="360513736"/>
<marker id="360513737"/>
<marker id="360513738"/>
<marker id="360513739"/>
<marker id="360513740"/>
<marker id="360513741"/>
<marker id="360513742"/>
<marker id="360513743"/>
<marker id="360513744"/>
<marker id="360513745"/>
<marker id="360513746"/>
<marker id="360513747"/>
<marker id="360517632"/>
<marker id="360517633"/>
<marker id="360517634"/>
<marker id="360517635"/>
<marker id="360517636"/>
<marker id="360517637"/>
<marker id="360517638"/>
<marker id="360517639"/>
<marker id="360517640"/>
<marker id="360517641"/>
<marker id="360517642"/>
<marker id="360517643"/>
<marker id="360517644"/>
<marker id="360517645"/>
<marker id="360517646"/>
<marker id="360517647"/>
<marker id="360517648"/>
<marker id="360517649"/>
<marker id="360517650"/>
<marker id="360517651"/>
<marker id="360517652"/>
<marker id="360517653"/>
<marker id="360517654"/>
<marker id="360517655"/>
<marker id="360517656"/>
<marker id="360517657"/>
<marker id="360517658"/>
<marker id="360517659"/>
<marker id="360517660"/>
<marker id="360517661"/>
<marker id="360517662"/>
<marker id="360517663"/>
<marker id="360517664"/>
<marker id="360517665"/>
<marker id="360517666"/>
<marker id="360517667"/>
<marker id="360517668"/>
<marker id="360517669"/>
<marker id="360517670"/>
<marker id="360517671"/>
<marker id="360517672"/>
<marker id="360517673"/>
<marker id="360517674"/>
<marker id="360517675"/>
<marker id="360517676"/>
<marker id="360517677"/>
<marker id="360517678"/>
<marker id="360517679"/>
<marker id="360517680"/>
<marker id="360517681"/>
<marker id="360517682"/>
<marker id="360517683"/>
<marker id="360517684"/>
<marker id="360517685"/>
<marker id="360517686"/>
<marker id="360517687"/>
<marker id="360517688"/>
<marker id="360517689"/>
<marker id="360517690"/>
<marker id="360517691"/>
<marker id="360517692"/>
<marker id="360517693"/>
<marker id="360517694"/>
<marker id="360517695"/>
<marker id="360517696"/>
<marker id="360517697"/>
<marker id="360517698"/>
<marker id="360517699"/>
<marker id="360517700"/>
<marker id="360517701"/>
<marker id="360517702"/>
<marker id="360517703"/>
<marker id="360517704"/>
<marker id="360517705"/>
<marker id="360517706"/>
<marker id="360517707"/>
<marker id="360517708"/>
<marker id="360517709"/>
<marker id="360517710"/>
<marker id="360517711"/>
<marker id="360517712"/>
<marker id="360517713"/>
<marker id="360517714"/>
<marker id="360517715"/>
<marker id="360517716"/>
<marker id="360517717"/>
<marker id="360517718"/>
<marker id="360517719"/>
<marker id="360517720"/>
<marker id="360517721"/>
<marker id="360517722"/>
<marker id="360517723"/>
<marker id="360517724"/>
<marker id="360517725"/>
<marker id="360517726"/>
<marker id="360517727"/>
<marker id="360517728"/>
<marker id="360517729"/>
<marker id="360517730"/>
<marker id="360517731"/>
<marker id="360517732"/>
<marker id="360517733"/>
<marker id="360517734"/>
<marker id="360517735"/>
<marker id="360517736"/>
<marker id="360517737"/>
<marker id="360517738"/>
<marker id="360517739"/>
<marker id="360517740"/>
<marker id="360517741"/>
<marker id="360517742"/>
<marker id="360517743"/>
<marker id="360517744"/>
<marker id="360517745"/>
<marker id="360517746"/>
<marker id="360517747"/>
<marker id="360517748"/>
<marker id="360517749"/>
<marker id="360517750"/>
<marker id="360517751"/>
<marker id="360517752"/>
<marker id="360517753"/>
<marker id="360517754"/>
<marker id="360517755"/>
<marker id="360517756"/>
<marker id="360517757"/>
<marker id="360517758"/>
<marker id="360517759"/>
<marker id="360517760"/>
<marker id="360517761"/>
<marker id="360517762"/>
<marker id="360517763"/>
<marker id="360517764"/>
<marker id="360517765"/>
<marker id="360517766"/>
<marker id="360517767"/>
<marker id="360517768"/>
<marker id="360517769"/>
<marker id="360517770"/>
<marker id="360517771"/>
<marker id="360517772"/>
<marker id="360517773"/>
<marker id="360517774"/>
<marker id="360517775"/>
<marker id="360517776"/>
<marker id="360517777"/>
<marker id="360517778"/>
<marker id="360517779"/>
<marker id="360517780"/>
<marker id="360517781"/>
<marker id="360517782"/>
<marker id="360517783"/>
<marker id="360517784"/>
<marker id="360517785"/>
<marker id="360517786"/>
<marker id="360517787"/>
<marker id="360521728"/>
<marker id="360521729"/>
<marker id="360521730"/>
<marker id="360521731"/>
<marker id="360521732"/>
<marker id="360521733"/>
<marker id="360521734"/>
<marker id="360521735"/>
<marker id="360521736"/>
<marker id="360521737"/>
<marker id="360521738"/>
<marker id="360521739"/>
<marker id="360521740"/>
<marker id="360521741"/>
<marker id="360521742"/>
<marker id="360521743"/>
<marker id="360521744"/>
<marker id="360521745"/>
<marker id="360521746"/>
<marker id="360521747"/>
<marker id="360521748"/>
<marker id="360521749"/>
<marker id="360521750"/>
<marker id="360521751"/>
<marker id="360521752"/>
<marker id="360521753"/>
<marker id="360521754"/>
<marker id="360521755"/>
<marker id="360521756"/>
<marker id="360521757"/>
<marker id="360521758"/>
<marker id="360521759"/>
<marker id="360521760"/>
<marker id="360521761"/>
<marker id="360521762"/>
<marker id="360521763"/>
<marker id="360521764"/>
<marker id="360521765"/>
<marker id="360521766"/>
<marker id="360521767"/>
<marker id="360521768"/>
<marker id="360521769"/>
<marker id="360521770"/>
<marker id="360521771"/>
<marker id="360521772"/>
<marker id="360521773"/>
<marker id="360521774"/>
<marker id="360521775"/>
<marker id="360521776"/>
<marker id="360521777"/>
<marker id="360521778"/>
<marker id="360521779"/>
<marker id="360521780"/>
<marker id="360521781"/>
<marker id="360521782"/>
<marker id="360521783"/>
<marker id="360521784"/>
<marker id="360521785"/>
<marker id="360521786"/>
<marker id="360521787"/>
<marker id="360521788"/>
<marker id="360521789"/>
<marker id="360521790"/>
<marker id="360521791"/>
<marker id="360521792"/>
<marker id="360521793"/>
<marker id="360521794"/>
<marker id="360521795"/>
<marker id="360521796"/>
<marker id="360521797"/>
<marker id="360521798"/>
<marker id="360521799"/>
<marker id="360521800"/>
<marker id="360521801"/>
<marker id="360521802"/>
<marker id="360521803"/>
<marker id="360521804"/>
<marker id="360521805"/>
<marker id="360521806"/>
<marker id="360521807"/>
<marker id="360521808"/>
<marker id="360521809"/>
<marker id="360521810"/>
<marker id="360521811"/>
<marker id="360521812"/>
<marker id="360521813"/>
<marker id="360521814"/>
<marker id="360521815"/>
<marker id="360521816"/>
<marker id="360521817"/>
<marker id="360521818"/>
<marker id="360521819"/>
<marker id="360521820"/>
<marker id="360521821"/>
<marker id="360521822"/>
<marker id="360521823"/>
<marker id="360521824"/>
<marker id="360521825"/>
<marker id="360521826"/>
<marker id="360521827"/>
<marker id="360521828"/>
<marker id="360521829"/>
<marker id="360521830"/>
<marker id="360521831"/>
<marker id="360521832"/>
<marker id="360521833"/>
<marker id="360521834"/>
<marker id="360521835"/>
<marker id="360521836"/>
<marker id="360521837"/>
<marker id="360521838"/>
<marker id="360521839"/>
<marker id="360521840"/>
<marker id="360521841"/>
<marker id="360521842"/>
<marker id="360521843"/>
<marker id="360521844"/>
<marker id="360521845"/>
<marker id="360521846"/>
<marker id="360521847"/>
<marker id="360521848"/>
<marker id="360521849"/>
<marker id="360521850"/>
<marker id="360521851"/>
<marker id="360521852"/>
<marker id="360521853"/>
<marker id="360521854"/>
<marker id="360521855"/>
<marker id="360521856"/>
<marker id="360521857"/>
<marker id="360521858"/>
<marker id="360521859"/>
<marker id="360521860"/>
<marker id="360521861"/>
<marker id="360521862"/>
<marker id="360521863"/>
<marker id="360521864"/>
<marker id="360521865"/>
<marker id="360521866"/>
<marker id="360521867"/>
<marker id="360521868"/>
<marker id="360521869"/>
<marker id="360521870"/>
<marker id="360521871"/>
<marker id="360521872"/>
<marker id="360521873"/>
<marker id="360521874"/>
<marker id="360521875"/>
<marker id="360521876"/>
<marker id="360521877"/>
<marker id="360521878"/>
<marker id="360521879"/>
<marker id="360521880"/>
<marker id="360521881"/>
<marker id="360521882"/>
<marker id="360521883"/>
<marker id="360521884"/>
<marker id="360521885"/>
<marker id="360521886"/>
<marker id="360521887"/>
<marker id="360521888"/>
<marker id="360521889"/>
<marker id="360521890"/>
<marker id="360521891"/>
<marker id="360521892"/>
<marker id="360521893"/>
<marker id="360521894"/>
<marker id="360521895"/>
<marker id="360521896"/>
<marker id="360521897"/>
<marker id="360521898"/>
<marker id="360521899"/>
<marker id="360521900"/>
<marker id="360521901"/>
<marker id="360521902"/>
<marker id="360521903"/>
<marker id="360521904"/>
<marker id="360521905"/>
<marker id="360521906"/>
<marker id="360521907"/>
<marker id="360521908"/>
<marker id="360521909"/>
<marker id="360521910"/>
<marker id="360521911"/>
<marker id="360521912"/>
<marker id="360521913"/>
<marker id="360521914"/>
<marker id="360521915"/>
<marker id="360521916"/>
<marker id="360521917"/>
<marker id="360579072"/>
<marker id="360579073"/>
<marker id="360579074"/>
<marker id="360579075"/>
<marker id="360579076"/>
<marker id="360579077"/>
<marker id="360579078"/>
<marker id="360579079"/>
<marker id="360579080"/>
<marker id="360579081"/>
<marker id="360579082"/>
<marker id="360579083"/>
<marker id="360579084"/>
<marker id="360579085"/>
<marker id="360579086"/>
<marker id="360579087"/>
<marker id="360579088"/>
<marker id="360579089"/>
<marker id="360579090"/>
<marker id="360579091"/>
<marker id="360579092"/>
<marker id="360579093"/>
<marker id="360579094"/>
<marker id="360579095"/>
<marker id="360579096"/>
<marker id="360579097"/>
<marker id="360579098"/>
<marker id="360579099"/>
<marker id="360579100"/>
<marker id="360579101"/>
<marker id="360579102"/>
<marker id="360579103"/>
<marker id="360579104"/>
<marker id="360579105"/>
<marker id="360579106"/>
<marker id="360579107"/>
<marker id="360579108"/>
<marker id="360579109"/>
<marker id="360579110"/>
<marker id="360579111"/>
<marker id="360579112"/>
<marker id="360579113"/>
<marker id="360579114"/>
<marker id="360579115"/>
<marker id="360579116"/>
<marker id="360579117"/>
<marker id="360579118"/>
<marker id="360579119"/>
<marker id="360579120"/>
<marker id="360579121"/>
<marker id="360579122"/>
<marker id="360579123"/>
<marker id="360579124"/>
<marker id="360579125"/>
<marker id="360579126"/>
<marker id="360579127"/>
<marker id="360579128"/>
<marker id="360579129"/>
<marker id="360579130"/>
<marker id="360579131"/>
<marker id="360579132"/>
<marker id="360579133"/>
<marker id="360579134"/>
<marker id="360579135"/>
<marker id="360579136"/>
<marker id="360579137"/>
<marker id="360579138"/>
<marker id="360579139"/>
<marker id="360579140"/>
<marker id="360579141"/>
<marker id="360583168"/>
<marker id="360587264"/>
<marker id="360587265"/>
<marker id="360587266"/>
<marker id="360587267"/>
<marker id="360587268"/>
<marker id="360587269"/>
<marker id="360587270"/>
<marker id="360587271"/>
<marker id="360587272"/>
<marker id="360587273"/>
<marker id="360587274"/>
<marker id="360587275"/>
<marker id="360587276"/>
<marker id="360587277"/>
<marker id="360587278"/>
<marker id="360587279"/>
<marker id="360587280"/>
<marker id="360587281"/>
<marker id="360587282"/>
<marker id="360587283"/>
<marker id="360587284"/>
<marker id="360587285"/>
<marker id="360587286"/>
<marker id="360587287"/>
<marker id="360587288"/>
<marker id="360587289"/>
<marker id="360587290"/>
<marker id="360587291"/>
<marker id="360587292"/>
<marker id="360587293"/>
<marker id="360587294"/>
<marker id="360587295"/>
<marker id="360587296"/>
<marker id="360587297"/>
<marker id="360587298"/>
<marker id="360587299"/>
<marker id="360587300"/>
<marker id="360587301"/>
<marker id="360587302"/>
<marker id="360587303"/>
<marker id="360587304"/>
<marker id="360587305"/>
<marker id="360587306"/>
<marker id="360587307"/>
<marker id="360587308"/>
<marker id="360587309"/>
<marker id="360587310"/>
<marker id="360587311"/>
<marker id="360587312"/>
<marker id="360587313"/>
<marker id="360587314"/>
<marker id="360587315"/>
<marker id="360587316"/>
<marker id="360587317"/>
<marker id="360587318"/>
<marker id="360587319"/>
<marker id="360587320"/>
<marker id="360587321"/>
<marker id="360587322"/>
<marker id="360587323"/>
<marker id="360587324"/>
<marker id="360587325"/>
<marker id="360587326"/>
<marker id="360587327"/>
<marker id="360587328"/>
<marker id="360587329"/>
<marker id="360587330"/>
<marker id="360587331"/>
<marker id="360587332"/>
<marker id="360587333"/>
<marker id="360587334"/>
<marker id="360587335"/>
<marker id="360587336"/>
<marker id="360587337"/>
<marker id="360587338"/>
<marker id="360644608"/>
<marker id="360644609"/>
<marker id="360644610"/>
<marker id="360644611"/>
<marker id="360644612"/>
<marker id="360644613"/>
<marker id="360644614"/>
<marker id="360644615"/>
<marker id="360644616"/>
<marker id="360644617"/>
<marker id="360644618"/>
<marker id="360644619"/>
<marker id="360644620"/>
<marker id="360644621"/>
<marker id="360644622"/>
<marker id="360644623"/>
<marker id="360644624"/>
<marker id="360644625"/>
<marker id="360644626"/>
<marker id="360644627"/>
<marker id="360644628"/>
<marker id="360644629"/>
<marker id="360644630"/>
<marker id="360644631"/>
<marker id="360644632"/>
<marker id="360644633"/>
<marker id="360644634"/>
<marker id="360644635"/>
<marker id="360644636"/>
<marker id="360644637"/>
<marker id="360644638"/>
<marker id="360644639"/>
<marker id="360644640"/>
<marker id="360644641"/>
<marker id="360644642"/>
<marker id="360644643"/>
<marker id="360644644"/>
<marker id="360644645"/>
<marker id="360644646"/>
<marker id="360644647"/>
<marker id="360644648"/>
<marker id="360644649"/>
<marker id="360644650"/>
<marker id="360644651"/>
<marker id="360644652"/>
<marker id="360644653"/>
<marker id="360644654"/>
<marker id="360644655"/>
<marker id="360644656"/>
<marker id="360644657"/>
<marker id="360644658"/>
<marker id="360644659"/>
<marker id="360644660"/>
<marker id="360644661"/>
<marker id="360644662"/>
<marker id="360644663"/>
<marker id="360644664"/>
<marker id="360644665"/>
<marker id="360644666"/>
<marker id="360644667"/>
<marker id="360644668"/>
<marker id="360644669"/>
<marker id="360644670"/>
<marker id="360644671"/>
<marker id="360644672"/>
<marker id="360644673"/>
<marker id="360644674"/>
<marker id="360644675"/>
<marker id="360644676"/>
<marker id="360644677"/>
<marker id="360644678"/>
<marker id="360644679"/>
<marker id="360644680"/>
<marker id="360644681"/>
<marker id="360644682"/>
<marker id="360644683"/>
<marker id="360644684"/>
<marker id="360644685"/>
<marker id="360644686"/>
<marker id="360644687"/>
<marker id="360644688"/>
<marker id="360644689"/>
<marker id="360644690"/>
<marker id="360644691"/>
<marker id="360644692"/>
<marker id="360644693"/>
<marker id="360644694"/>
<marker id="360644695"/>
<marker id="360644696"/>
<marker id="360644697"/>
<marker id="360644698"/>
<marker id="360644699"/>
<marker id="360644700"/>
<marker id="360644701"/>
<marker id="360644702"/>
<marker id="360644703"/>
<marker id="360644704"/>
<marker id="360644705"/>
<marker id="360644706"/>
<marker id="360644707"/>
<marker id="360644708"/>
<marker id="360644709"/>
<marker id="360644710"/>
<marker id="360644711"/>
<marker id="360644712"/>
<marker id="360644713"/>
<marker id="360644714"/>
<marker id="360644715"/>
<marker id="360644716"/>
<marker id="360644717"/>
<marker id="360644718"/>
<marker id="360644719"/>
<marker id="360644720"/>
<marker id="360644721"/>
<marker id="360644722"/>
<marker id="360644723"/>
<marker id="360644724"/>
<marker id="360644725"/>
<marker id="360644726"/>
<marker id="360644727"/>
<marker id="360644728"/>
<marker id="360644729"/>
<marker id="360644730"/>
<marker id="360644731"/>
<marker id="360644732"/>
<marker id="360644733"/>
<marker id="360644734"/>
<marker id="360644735"/>
<marker id="360644736"/>
<marker id="360644737"/>
<marker id="360644738"/>
<marker id="360644739"/>
<marker id="360644740"/>
<marker id="360644741"/>
<marker id="360644742"/>
<marker id="360644743"/>
<marker id="360644744"/>
<marker id="360644745"/>
<marker id="360644746"/>
<marker id="360644747"/>
<marker id="360644748"/>
<marker id="360644749"/>
<marker id="360644750"/>
<marker id="360644751"/>
<marker id="360644752"/>
<marker id="360644753"/>
<marker id="360644754"/>
<marker id="360644755"/>
<marker id="360644756"/>
<marker id="360644757"/>
<marker id="360644758"/>
<marker id="360644759"/>
<marker id="360644760"/>
<marker id="360644761"/>
<marker id="360644762"/>
<marker id="360644763"/>
<marker id="360644764"/>
<marker id="360644765"/>
<marker id="360644766"/>
<marker id="360644767"/>
<marker id="360644768"/>
<marker id="360644769"/>
<marker id="360644770"/>
<marker id="360644771"/>
<marker id="360644772"/>
<marker id="360644773"/>
<marker id="360644774"/>
<marker id="360644775"/>
<marker id="360644776"/>
<marker id="360644777"/>
<marker id="360644778"/>
<marker id="360644779"/>
<marker id="360644780"/>
<marker id="360644781"/>
<marker id="360644782"/>
<marker id="360644783"/>
<marker id="360644784"/>
<marker id="360644785"/>
<marker id="360644786"/>
<marker id="360644787"/>
<marker id="360644788"/>
<marker id="360644789"/>
<marker id="360644790"/>
<marker id="360644791"/>
<marker id="360644792"/>
<marker id="360644793"/>
<marker id="360644794"/>
<marker id="360644795"/>
<marker id="360644796"/>
<marker id="360644797"/>
<marker id="360644798"/>
<marker id="360644799"/>
<marker id="360644800"/>
<marker id="360644801"/>
<marker id="360644802"/>
<marker id="360644803"/>
<marker id="360644804"/>
<marker id="360644805"/>
<marker id="360644806"/>
<marker id="360644807"/>
<marker id="360644808"/>
<marker id="360644809"/>
<marker id="360648704"/>
<marker id="360648705"/>
<marker id="360648706"/>
<marker id="360648707"/>
<marker id="360648708"/>
<marker id="360648709"/>
<marker id="360648710"/>
<marker id="360648711"/>
<marker id="360648712"/>
<marker id="360648713"/>
<marker id="360648714"/>
<marker id="360648715"/>
<marker id="360648716"/>
<marker id="360648717"/>
<marker id="360648718"/>
<marker id="360648719"/>
<marker id="360648720"/>
<marker id="360648721"/>
<marker id="360648722"/>
<marker id="360648723"/>
<marker id="360648724"/>
<marker id="360648725"/>
<marker id="360648726"/>
<marker id="360648727"/>
<marker id="360648728"/>
<marker id="360648729"/>
<marker id="360648730"/>
<marker id="360648731"/>
<marker id="360648732"/>
<marker id="360648733"/>
<marker id="360648734"/>
<marker id="360648735"/>
<marker id="360648736"/>
<marker id="360648737"/>
<marker id="360648738"/>
<marker id="360648739"/>
<marker id="360648740"/>
<marker id="360648741"/>
<marker id="360648742"/>
<marker id="360648743"/>
<marker id="360648744"/>
<marker id="360648745"/>
<marker id="360648746"/>
<marker id="360648747"/>
<marker id="360648748"/>
<marker id="360648749"/>
<marker id="360648750"/>
<marker id="360648751"/>
<marker id="360648752"/>
<marker id="360648753"/>
<marker id="360648754"/>
<marker id="360648755"/>
<marker id="360648756"/>
<marker id="360648757"/>
<marker id="360648758"/>
<marker id="360648759"/>
<marker id="360648760"/>
<marker id="360648761"/>
<marker id="360648762"/>
<marker id="360648763"/>
<marker id="360648764"/>
<marker id="360648765"/>
<marker id="360648766"/>
<marker id="360648767"/>
<marker id="360648768"/>
<marker id="360648769"/>
<marker id="360648770"/>
<marker id="360648771"/>
<marker id="360648772"/>
<marker id="360648773"/>
<marker id="360648774"/>
<marker id="360648775"/>
<marker id="360648776"/>
<marker id="360648777"/>
<marker id="360648778"/>
<marker id="360648779"/>
<marker id="360648780"/>
<marker id="360648781"/>
<marker id="360648782"/>
<marker id="360648783"/>
<marker id="360648784"/>
<marker id="360648785"/>
<marker id="360648786"/>
<marker id="360648787"/>
<marker id="360648788"/>
<marker id="360648789"/>
<marker id="360648790"/>
<marker id="360648791"/>
<marker id="360648792"/>
<marker id="360648793"/>
<marker id="360648794"/>
<marker id="360648795"/>
<marker id="360648796"/>
<marker id="360648797"/>
<marker id="360648798"/>
<marker id="360648799"/>
<marker id="360648800"/>
<marker id="360648801"/>
<marker id="360648802"/>
<marker id="360648803"/>
<marker id="360648804"/>
<marker id="360648805"/>
<marker id="360648806"/>
<marker id="360648807"/>
<marker id="360648808"/>
<marker id="360648809"/>
<marker id="360648810"/>
<marker id="360648811"/>
<marker id="360648812"/>
<marker id="360648813"/>
<marker id="360648814"/>
<marker id="360648815"/>
<marker id="360648816"/>
<marker id="360648817"/>
<marker id="360648818"/>
<marker id="360648819"/>
<marker id="360648820"/>
<marker id="360648821"/>
<marker id="360648822"/>
<marker id="360648823"/>
<marker id="360648824"/>
<marker id="360648825"/>
<marker id="360648826"/>
<marker id="360648827"/>
<marker id="360648828"/>
<marker id="360648829"/>
<marker id="360648830"/>
<marker id="360648831"/>
<marker id="360648832"/>
<marker id="360648833"/>
<marker id="360648834"/>
<marker id="360648835"/>
<marker id="360648836"/>
<marker id="360648837"/>
<marker id="360648838"/>
<marker id="360648839"/>
<marker id="360648840"/>
<marker id="360648841"/>
<marker id="360648842"/>
<marker id="360648843"/>
<marker id="360648844"/>
<marker id="360648845"/>
<marker id="360648846"/>
<marker id="360648847"/>
<marker id="360648848"/>
<marker id="360648849"/>
<marker id="360648850"/>
<marker id="360648851"/>
<marker id="360648852"/>
<marker id="360648853"/>
<marker id="360648854"/>
<marker id="360648855"/>
<marker id="360648856"/>
<marker id="360648857"/>
<marker id="360648858"/>
<marker id="360648859"/>
<marker id="360648860"/>
<marker id="360648861"/>
<marker id="360648862"/>
<marker id="360648863"/>
<marker id="360648864"/>
<marker id="360648865"/>
<marker id="360648866"/>
<marker id="360648867"/>
<marker id="360648868"/>
<marker id="360648869"/>
<marker id="360648870"/>
<marker id="360648871"/>
<marker id="360648872"/>
<marker id="360648873"/>
<marker id="360648874"/>
<marker id="360648875"/>
<marker id="360648876"/>
<marker id="360648877"/>
<marker id="360648878"/>
<marker id="360648879"/>
<marker id="360648880"/>
<marker id="360648881"/>
<marker id="360648882"/>
<marker id="360648883"/>
<marker id="360648884"/>
<marker id="360648885"/>
<marker id="360648886"/>
<marker id="360648887"/>
<marker id="360648888"/>
<marker id="360648889"/>
<marker id="360648890"/>
<marker id="360648891"/>
<marker id="360648892"/>
<marker id="360648893"/>
<marker id="360648894"/>
<marker id="360648895"/>
<marker id="360648896"/>
<marker id="360648897"/>
<marker id="360648898"/>
<marker id="360648899"/>
<marker id="360648900"/>
<marker id="360648901"/>
<marker id="360648902"/>
<marker id="360648903"/>
<marker id="360648904"/>
<marker id="360648905"/>
<marker id="360648906"/>
<marker id="360652800"/>
<marker id="360652801"/>
<marker id="360652802"/>
<marker id="360652803"/>
<marker id="360652804"/>
<marker id="360652805"/>
<marker id="360652806"/>
<marker id="360652807"/>
<marker id="360652808"/>
<marker id="360652809"/>
<marker id="360652810"/>
<marker id="360652811"/>
<marker id="360652812"/>
<marker id="360652813"/>
<marker id="360652814"/>
<marker id="360652815"/>
<marker id="360652816"/>
<marker id="360652817"/>
<marker id="360652818"/>
<marker id="360652819"/>
<marker id="360652820"/>
<marker id="360652821"/>
<marker id="360652822"/>
<marker id="360652823"/>
<marker id="360652824"/>
<marker id="360652825"/>
<marker id="360652826"/>
<marker id="360652827"/>
<marker id="360652828"/>
<marker id="360652829"/>
<marker id="360652830"/>
<marker id="360652831"/>
<marker id="360652832"/>
<marker id="360652833"/>
<marker id="360652834"/>
<marker id="360652835"/>
<marker id="360652836"/>
<marker id="360652837"/>
<marker id="360652838"/>
<marker id="360652839"/>
<marker id="360652840"/>
<marker id="360652841"/>
<marker id="360652842"/>
<marker id="360652843"/>
<marker id="360652844"/>
<marker id="360652845"/>
<marker id="360652846"/>
<marker id="360652847"/>
<marker id="360652848"/>
<marker id="360652849"/>
<marker id="360652850"/>
<marker id="360652851"/>
<marker id="360652852"/>
<marker id="360652853"/>
<marker id="360652854"/>
<marker id="360652855"/>
<marker id="360652856"/>
<marker id="360652857"/>
<marker id="360652858"/>
<marker id="360652859"/>
<marker id="360652860"/>
<marker id="360652861"/>
<marker id="360652862"/>
<marker id="360652863"/>
<marker id="360652864"/>
<marker id="360652865"/>
<marker id="360652866"/>
<marker id="360652867"/>
<marker id="360652868"/>
<marker id="360652869"/>
<marker id="360652870"/>
<marker id="360652871"/>
<marker id="360652872"/>
<marker id="360652873"/>
<marker id="360652874"/>
<marker id="360652875"/>
<marker id="360652876"/>
<marker id="360652877"/>
<marker id="360652878"/>
<marker id="360652879"/>
<marker id="360652880"/>
<marker id="360652881"/>
<marker id="360652882"/>
<marker id="360652883"/>
<marker id="360652884"/>
<marker id="360652885"/>
<marker id="360652886"/>
<marker id="360652887"/>
<marker id="360652888"/>
<marker id="360652889"/>
<marker id="360652890"/>
<marker id="360652891"/>
<marker id="360652892"/>
<marker id="360652893"/>
<marker id="360652894"/>
<marker id="360652895"/>
<marker id="360652896"/>
<marker id="360652897"/>
<marker id="360652898"/>
<marker id="360652899"/>
<marker id="360652900"/>
<marker id="360652901"/>
<marker id="360652902"/>
<marker id="360652903"/>
<marker id="360652904"/>
<marker id="360652905"/>
<marker id="360652906"/>
<marker id="360652907"/>
<marker id="360652908"/>
<marker id="360652909"/>
<marker id="360652910"/>
<marker id="360652911"/>
<marker id="360652912"/>
<marker id="360652913"/>
<marker id="360652914"/>
<marker id="360652915"/>
<marker id="360652916"/>
<marker id="360652917"/>
<marker id="360652918"/>
<marker id="360652919"/>
<marker id="360652920"/>
<marker id="360652921"/>
<marker id="360652922"/>
<marker id="360652923"/>
<marker id="360652924"/>
<marker id="360652925"/>
<marker id="360652926"/>
<marker id="360652927"/>
<marker id="360652928"/>
<marker id="360652929"/>
<marker id="360652930"/>
<marker id="360652931"/>
<marker id="360652932"/>
<marker id="360652933"/>
<marker id="360652934"/>
<marker id="360652935"/>
<marker id="360652936"/>
<marker id="360652937"/>
<marker id="360652938"/>
<marker id="360652939"/>
<marker id="360652940"/>
<marker id="360652941"/>
<marker id="360652942"/>
<marker id="360652943"/>
<marker id="360652944"/>
<marker id="360652945"/>
<marker id="360652946"/>
<marker id="360652947"/>
<marker id="360652948"/>
<marker id="360652949"/>
<marker id="360652950"/>
<marker id="376438784"/>
<marker id="376438785"/>
<marker id="376438786"/>
<marker id="376438787"/>
<marker id="376438788"/>
<marker id="376438789"/>
<marker id="376438790"/>
<marker id="376438791"/>
<marker id="376438792"/>
<marker id="376438793"/>
<marker id="376438794"/>
<marker id="376438795"/>
<marker id="376438796"/>
<marker id="376438797"/>
<marker id="376438798"/>
<marker id="376438799"/>
<marker id="376438800"/>
<marker id="376438801"/>
<marker id="376438802"/>
<marker id="376438803"/>
<marker id="376438804"/>
<marker id="376438805"/>
<marker id="376438806"/>
<marker id="376438807"/>
<marker id="376438808"/>
<marker id="376438809"/>
<marker id="376438810"/>
<marker id="376438811"/>
<marker id="376438812"/>
<marker id="376438813"/>
<marker id="376438814"/>
<marker id="376438815"/>
<marker id="376438816"/>
<marker id="376438817"/>
<marker id="376438818"/>
<marker id="376438819"/>
<marker id="376438820"/>
<marker id="376438821"/>
<marker id="376438822"/>
<marker id="376438823"/>
<marker id="376438824"/>
<marker id="376438825"/>
<marker id="376438826"/>
<marker id="376438827"/>
<marker id="376438828"/>
<marker id="376438829"/>
<marker id="376438830"/>
<marker id="376438831"/>
<marker id="376438832"/>
<marker id="376438833"/>
<marker id="376438834"/>
<marker id="376438835"/>
<marker id="376438836"/>
<marker id="376438837"/>
<marker id="376438838"/>
<marker id="376438839"/>
<marker id="376438840"/>
<marker id="376438841"/>
<marker id="376438842"/>
<marker id="376438843"/>
<marker id="376438844"/>
<marker id="376438845"/>
<marker id="376438846"/>
<marker id="376438847"/>
<marker id="376438848"/>
<marker id="376438849"/>
<marker id="376438850"/>
<marker id="376438851"/>
<marker id="376438852"/>
<marker id="376438853"/>
<marker id="376438854"/>
<marker id="376438855"/>
<marker id="376438856"/>
<marker id="376438857"/>
<marker id="376438858"/>
<marker id="376438859"/>
<marker id="376438860"/>
<marker id="376438861"/>
<marker id="376438862"/>
<marker id="376438863"/>
<marker id="376438864"/>
<marker id="376438865"/>
<marker id="376438866"/>
<marker id="376438867"/>
<marker id="376438868"/>
<marker id="376438869"/>
<marker id="376438870"/>
<marker id="376438871"/>
<marker id="376438872"/>
<marker id="376438873"/>
<marker id="376438874"/>
<marker id="376438875"/>
<marker id="376438876"/>
<marker id="376438877"/>
<marker id="376438878"/>
<marker id="376438879"/>
<marker id="376438880"/>
<marker id="376438881"/>
<marker id="376438882"/>
<marker id="376438883"/>
<marker id="376438884"/>
<marker id="376438885"/>
<marker id="376438886"/>
<marker id="376438887"/>
<marker id="376438888"/>
<marker id="376438889"/>
<marker id="376438890"/>
<marker id="376438891"/>
<marker id="376438892"/>
<marker id="376438893"/>
<marker id="376438894"/>
<marker id="376438895"/>
<marker id="376438896"/>
<marker id="376438897"/>
<marker id="376438898"/>
<marker id="376438899"/>
<marker id="376438900"/>
<marker id="376438901"/>
<marker id="376438902"/>
<marker id="376438903"/>
<marker id="376438904"/>
<marker id="376438905"/>
<marker id="376438906"/>
<marker id="376438907"/>
<marker id="376438908"/>
<marker id="376438909"/>
<marker id="376438910"/>
<marker id="376438911"/>
<marker id="376438912"/>
<marker id="376438913"/>
<marker id="376438914"/>
<marker id="376438915"/>
<marker id="376438916"/>
<marker id="376438917"/>
<marker id="376438918"/>
<marker id="376438919"/>
<marker id="376438920"/>
<marker id="376438921"/>
<marker id="376438922"/>
<marker id="376438923"/>
<marker id="376442880"/>
<marker id="376442881"/>
<marker id="376442882"/>
<marker id="376442883"/>
<marker id="376442884"/>
<marker id="376442885"/>
<marker id="376442886"/>
<marker id="376442887"/>
<marker id="376442888"/>
<marker id="376442889"/>
<marker id="376442890"/>
<marker id="376442891"/>
<marker id="376442892"/>
<marker id="376442893"/>
<marker id="376442894"/>
<marker id="376442895"/>
<marker id="376442896"/>
<marker id="376442897"/>
<marker id="376442898"/>
<marker id="376442899"/>
<marker id="376442900"/>
<marker id="376442901"/>
<marker id="376442902"/>
<marker id="376442903"/>
<marker id="376442904"/>
<marker id="376442905"/>
<marker id="376442906"/>
<marker id="376442907"/>
<marker id="376442908"/>
<marker id="376442909"/>
<marker id="376442910"/>
<marker id="376442911"/>
<marker id="376442912"/>
<marker id="376442913"/>
<marker id="376442914"/>
<marker id="376442915"/>
<marker id="376442916"/>
<marker id="376442917"/>
<marker id="376442918"/>
<marker id="376442919"/>
<marker id="376442920"/>
<marker id="376442921"/>
<marker id="376442922"/>
<marker id="376442923"/>
<marker id="376442924"/>
<marker id="376442925"/>
<marker id="376442926"/>
<marker id="376442927"/>
<marker id="376442928"/>
<marker id="376442929"/>
<marker id="376442930"/>
<marker id="376442931"/>
<marker id="376442932"/>
<marker id="376442933"/>
<marker id="376442934"/>
<marker id="376442935"/>
<marker id="376442936"/>
<marker id="376442937"/>
<marker id="376442938"/>
<marker id="376442939"/>
<marker id="376442940"/>
<marker id="376442941"/>
<marker id="376442942"/>
<marker id="376442943"/>
<marker id="376442944"/>
<marker id="376442945"/>
<marker id="376442946"/>
<marker id="376442947"/>
<marker id="376442948"/>
<marker id="376442949"/>
<marker id="376442950"/>
<marker id="376442951"/>
<marker id="376442952"/>
<marker id="376442953"/>
<marker id="376442954"/>
<marker id="376442955"/>
<marker id="376442956"/>
<marker id="376442957"/>
<marker id="376442958"/>
<marker id="376442959"/>
<marker id="376442960"/>
<marker id="376442961"/>
<marker id="376442962"/>
<marker id="376442963"/>
<marker id="376442964"/>
<marker id="376442965"/>
<marker id="376442966"/>
<marker id="376442967"/>
<marker id="376442968"/>
<marker id="376442969"/>
<marker id="376442970"/>
<marker id="376442971"/>
<marker id="376442972"/>
<marker id="376442973"/>
<marker id="376442974"/>
<marker id="376442975"/>
<marker id="376442976"/>
<marker id="376442977"/>
<marker id="376442978"/>
<marker id="376442979"/>
<marker id="376442980"/>
<marker id="376442981"/>
<marker id="376442982"/>
<marker id="376442983"/>
<marker id="376442984"/>
<marker id="376442985"/>
<marker id="376442986"/>
<marker id="376442987"/>
<marker id="376442988"/>
<marker id="376442989"/>
<marker id="376442990"/>
<marker id="376442991"/>
<marker id="376442992"/>
<marker id="376442993"/>
<marker id="376442994"/>
<marker id="376442995"/>
<marker id="376442996"/>
<marker id="376442997"/>
<marker id="376442998"/>
<marker id="376442999"/>
<marker id="376443000"/>
<marker id="376443001"/>
<marker id="376443002"/>
<marker id="376443003"/>
<marker id="376443004"/>
<marker id="376443005"/>
<marker id="376443006"/>
<marker id="376443007"/>
<marker id="376443008"/>
<marker id="376443009"/>
<marker id="376443010"/>
<marker id="376443011"/>
<marker id="376443012"/>
<marker id="376443013"/>
<marker id="376443014"/>
<marker id="376443015"/>
<marker id="376443016"/>
<marker id="376443017"/>
<marker id="376443018"/>
<marker id="376443019"/>
<marker id="376443020"/>
<marker id="376443021"/>
<marker id="376443022"/>
<marker id="376443023"/>
<marker id="376443024"/>
<marker id="376443025"/>
<marker id="376443026"/>
<marker id="376443027"/>
<marker id="376443028"/>
<marker id="376443029"/>
<marker id="376443030"/>
<marker id="376443031"/>
<marker id="376443032"/>
<marker id="376443033"/>
<marker id="376443034"/>
<marker id="376443035"/>
<marker id="376443036"/>
<marker id="376443037"/>
<marker id="376443038"/>
<marker id="376443039"/>
<marker id="376443040"/>
<marker id="376443041"/>
<marker id="376443042"/>
<marker id="376443043"/>
<marker id="376443044"/>
<marker id="376443045"/>
<marker id="376443046"/>
<marker id="376443047"/>
<marker id="376443048"/>
<marker id="376443049"/>
<marker id="376443050"/>
<marker id="376443051"/>
<marker id="376443052"/>
<marker id="376443053"/>
<marker id="376443054"/>
<marker id="376443055"/>
<marker id="376443056"/>
<marker id="376443057"/>
<marker id="376443058"/>
<marker id="376443059"/>
<marker id="376443060"/>
<marker id="376443061"/>
<marker id="376443062"/>
<marker id="376443063"/>
<marker id="376443064"/>
<marker id="376443065"/>
<marker id="376443066"/>
<marker id="376443067"/>
<marker id="376443068"/>
<marker id="376443069"/>
<marker id="376443070"/>
<marker id="376443071"/>
<marker id="376443072"/>
<marker id="376443073"/>
<marker id="376443074"/>
<marker id="376443075"/>
<marker id="376443076"/>
<marker id="376443077"/>
<marker id="376443078"/>
<marker id="376443079"/>
<marker id="376443080"/>
<marker id="376443081"/>
<marker id="376443082"/>
<marker id="376443083"/>
<marker id="376443084"/>
<marker id="376443085"/>
<marker id="376443086"/>
<marker id="376443087"/>
<marker id="376443088"/>
<marker id="376443089"/>
<marker id="376443090"/>
<marker id="376443091"/>
<marker id="376443092"/>
<marker id="376443093"/>
<marker id="376443094"/>
<marker id="376443095"/>
<marker id="376443096"/>
<marker id="376443097"/>
<marker id="376443098"/>
<marker id="376443099"/>
<marker id="376443100"/>
<marker id="376443101"/>
<marker id="376443102"/>
<marker id="376443103"/>
<marker id="376443104"/>
<marker id="376443105"/>
<marker id="376443106"/>
<marker id="376443107"/>
<marker id="376443108"/>
<marker id="376443109"/>
<marker id="376443110"/>
<marker id="376443111"/>
<marker id="376443112"/>
<marker id="376443113"/>
<marker id="376443114"/>
<marker id="376443115"/>
<marker id="376443116"/>
<marker id="376443117"/>
<marker id="376443118"/>
<marker id="376443119"/>
<marker id="376443120"/>
<marker id="376443121"/>
<marker id="376446976"/>
<marker id="376446977"/>
<marker id="376446978"/>
<marker id="376446979"/>
<marker id="376446980"/>
<marker id="376446981"/>
<marker id="376446982"/>
<marker id="376446983"/>
<marker id="376446984"/>
<marker id="376446985"/>
<marker id="376446986"/>
<marker id="376446987"/>
<marker id="376446988"/>
<marker id="376446989"/>
<marker id="376446990"/>
<marker id="376446991"/>
<marker id="376446992"/>
<marker id="376446993"/>
<marker id="376446994"/>
<marker id="376446995"/>
<marker id="376446996"/>
<marker id="376446997"/>
<marker id="376446998"/>
<marker id="376446999"/>
<marker id="376447000"/>
<marker id="376447001"/>
<marker id="376447002"/>
<marker id="376447003"/>
<marker id="376447004"/>
<marker id="376447005"/>
<marker id="376447006"/>
<marker id="376447007"/>
<marker id="376447008"/>
<marker id="376447009"/>
<marker id="376447010"/>
<marker id="376447011"/>
<marker id="376447012"/>
<marker id="376447013"/>
<marker id="376447014"/>
<marker id="376447015"/>
<marker id="376447016"/>
<marker id="376447017"/>
<marker id="376447018"/>
<marker id="376447019"/>
<marker id="376447020"/>
<marker id="376447021"/>
<marker id="376447022"/>
<marker id="376447023"/>
<marker id="376447024"/>
<marker id="376447025"/>
<marker id="376447026"/>
<marker id="376447027"/>
<marker id="376447028"/>
<marker id="376447029"/>
<marker id="376447030"/>
<marker id="376447031"/>
<marker id="376447032"/>
<marker id="376447033"/>
<marker id="376447034"/>
<marker id="376447035"/>
<marker id="376447036"/>
<marker id="376447037"/>
<marker id="376447038"/>
<marker id="376447039"/>
<marker id="376447040"/>
<marker id="376447041"/>
<marker id="376447042"/>
<marker id="376447043"/>
<marker id="376447044"/>
<marker id="376447045"/>
<marker id="376447046"/>
<marker id="376447047"/>
<marker id="376447048"/>
<marker id="376447049"/>
<marker id="376447050"/>
<marker id="376447051"/>
<marker id="376447052"/>
<marker id="376447053"/>
<marker id="376447054"/>
<marker id="376447055"/>
<marker id="376447056"/>
<marker id="376447057"/>
<marker id="376447058"/>
<marker id="376447059"/>
<marker id="376447060"/>
<marker id="376447061"/>
<marker id="376447062"/>
<marker id="376447063"/>
<marker id="376447064"/>
<marker id="376447065"/>
<marker id="376447066"/>
<marker id="376447067"/>
<marker id="376447068"/>
<marker id="376447069"/>
<marker id="376447070"/>
<marker id="376447071"/>
<marker id="376447072"/>
<marker id="376447073"/>
<marker id="376447074"/>
<marker id="376447075"/>
<marker id="376447076"/>
<marker id="376447077"/>
<marker id="376447078"/>
<marker id="376447079"/>
<marker id="376447080"/>
<marker id="376447081"/>
<marker id="376447082"/>
<marker id="376447083"/>
<marker id="376447084"/>
</index>
