<?xml version="1.0" encoding="UTF-8"?><index key="1879077514">
<marker id="327016451"/>
<marker id="327016457"/>
<marker id="327016463"/>
<marker id="327016469"/>
<marker id="327016475"/>
<marker id="327016481"/>
<marker id="327016487"/>
<marker id="327016493"/>
<marker id="327016499"/>
<marker id="327016505"/>
<marker id="327077891"/>
<marker id="327077897"/>
<marker id="327077903"/>
<marker id="327077909"/>
<marker id="327077915"/>
<marker id="327077921"/>
<marker id="327077927"/>
<marker id="327077933"/>
<marker id="327077939"/>
<marker id="327077945"/>
<marker id="327086084"/>
<marker id="327086090"/>
<marker id="327086096"/>
<marker id="327086102"/>
<marker id="327086108"/>
<marker id="327086114"/>
<marker id="327086120"/>
<marker id="327086126"/>
<marker id="327086132"/>
<marker id="327086138"/>
<marker id="327147523"/>
<marker id="327147529"/>
<marker id="327147535"/>
<marker id="327147541"/>
<marker id="327147547"/>
<marker id="327147553"/>
<marker id="327147559"/>
<marker id="327147565"/>
<marker id="327147571"/>
<marker id="327147577"/>
<marker id="344137731"/>
<marker id="344137737"/>
<marker id="344137743"/>
<marker id="344137749"/>
<marker id="344137755"/>
<marker id="344137761"/>
<marker id="344137767"/>
<marker id="344137773"/>
<marker id="344137779"/>
<marker id="344137785"/>
<marker id="344145924"/>
<marker id="344145930"/>
<marker id="344145936"/>
<marker id="344145942"/>
<marker id="344145948"/>
<marker id="344145954"/>
<marker id="344145960"/>
<marker id="344145966"/>
<marker id="344145972"/>
<marker id="344145978"/>
<marker id="344207363"/>
<marker id="344207369"/>
<marker id="344207375"/>
<marker id="344207381"/>
<marker id="344207387"/>
<marker id="344207393"/>
<marker id="344207399"/>
<marker id="344207405"/>
<marker id="344207411"/>
<marker id="344207417"/>
<marker id="344215555"/>
<marker id="344215561"/>
<marker id="344215567"/>
<marker id="344215573"/>
<marker id="344215579"/>
<marker id="344215585"/>
<marker id="344215591"/>
<marker id="344215597"/>
<marker id="344215603"/>
<marker id="344215609"/>
<marker id="344276995"/>
<marker id="344277001"/>
<marker id="344277007"/>
<marker id="344277013"/>
<marker id="344277019"/>
<marker id="344277025"/>
<marker id="344277031"/>
<marker id="344277037"/>
<marker id="344277043"/>
<marker id="344277049"/>
<marker id="376369155"/>
<marker id="376369161"/>
<marker id="376369167"/>
<marker id="376369173"/>
<marker id="376369179"/>
<marker id="376369185"/>
<marker id="376369191"/>
<marker id="376369197"/>
<marker id="376369203"/>
<marker id="376369209"/>
<marker id="376430621"/>
<marker id="376430627"/>
<marker id="376430633"/>
<marker id="376430639"/>
<marker id="376430645"/>
<marker id="376430651"/>
<marker id="376430657"/>
<marker id="376430663"/>
<marker id="376430669"/>
<marker id="376430675"/>
<marker id="376606742"/>
<marker id="376606748"/>
<marker id="376606754"/>
<marker id="376606760"/>
<marker id="376606766"/>
<marker id="376606772"/>
<marker id="376606778"/>
<marker id="376606784"/>
<marker id="376606790"/>
<marker id="376615045"/>
<marker id="376615051"/>
<marker id="376615057"/>
<marker id="376615063"/>
<marker id="376615069"/>
<marker id="376615075"/>
<marker id="376615081"/>
<marker id="376615087"/>
<marker id="376615093"/>
<marker id="376615143"/>
<marker id="376668163"/>
<marker id="376668169"/>
<marker id="376668175"/>
<marker id="376668181"/>
<marker id="376668187"/>
<marker id="376668193"/>
<marker id="376668199"/>
<marker id="376668205"/>
<marker id="376668211"/>
<marker id="376676459"/>
<marker id="376676465"/>
<marker id="376676471"/>
<marker id="376676477"/>
<marker id="376676483"/>
<marker id="376676489"/>
<marker id="376676495"/>
<marker id="376676501"/>
<marker id="376676507"/>
<marker id="376676513"/>
<marker id="376684612"/>
<marker id="376684618"/>
<marker id="376684624"/>
<marker id="376684630"/>
<marker id="376684636"/>
<marker id="376684642"/>
<marker id="376684648"/>
<marker id="376684654"/>
<marker id="376684660"/>
<marker id="376684666"/>
<marker id="376737899"/>
<marker id="376737905"/>
<marker id="376737911"/>
<marker id="376737917"/>
<marker id="376737923"/>
<marker id="376737929"/>
<marker id="376737935"/>
<marker id="376737941"/>
<marker id="376737947"/>
<marker id="376737953"/>
<marker id="376741891"/>
<marker id="376741897"/>
<marker id="376741903"/>
<marker id="376741909"/>
<marker id="376741915"/>
<marker id="376741921"/>
<marker id="376741927"/>
<marker id="376741933"/>
<marker id="376741939"/>
<marker id="376741945"/>
<marker id="376741951"/>
<marker id="376741957"/>
<marker id="376741963"/>
<marker id="376741969"/>
<marker id="376741975"/>
<marker id="376741981"/>
<marker id="376741987"/>
<marker id="376741993"/>
<marker id="376741999"/>
<marker id="376742005"/>
<marker id="376742011"/>
<marker id="376742017"/>
<marker id="376742023"/>
<marker id="376742029"/>
<marker id="376795139"/>
<marker id="376795145"/>
<marker id="376795151"/>
<marker id="376795157"/>
<marker id="376795163"/>
<marker id="376795169"/>
<marker id="376795175"/>
<marker id="376795181"/>
<marker id="376795187"/>
<marker id="376795193"/>
<marker id="376795345"/>
<marker id="376795351"/>
<marker id="376795357"/>
<marker id="376795363"/>
<marker id="376795369"/>
<marker id="376795375"/>
<marker id="376795381"/>
<marker id="376795387"/>
<marker id="376795393"/>
<marker id="376795399"/>
<marker id="376795405"/>
<marker id="376795411"/>
<marker id="376795417"/>
<marker id="376795423"/>
<marker id="376864771"/>
<marker id="376864777"/>
<marker id="376864783"/>
<marker id="376864789"/>
<marker id="376864795"/>
<marker id="376864801"/>
<marker id="376864807"/>
<marker id="376864813"/>
<marker id="376864819"/>
<marker id="376864825"/>
<marker id="376864831"/>
<marker id="376864837"/>
<marker id="376864843"/>
<marker id="376864849"/>
<marker id="376864855"/>
<marker id="376864861"/>
<marker id="376864867"/>
<marker id="376864873"/>
<marker id="376873138"/>
<marker id="376873144"/>
<marker id="376873150"/>
<marker id="376873156"/>
<marker id="376873162"/>
<marker id="376873168"/>
<marker id="376873174"/>
<marker id="376873180"/>
<marker id="376873186"/>
<marker id="376873192"/>
<marker id="376873198"/>
<marker id="376873204"/>
<marker id="376873210"/>
<marker id="376873216"/>
<marker id="376873222"/>
<marker id="376873228"/>
<marker id="376873234"/>
<marker id="376873240"/>
<marker id="376926476"/>
<marker id="376926482"/>
<marker id="376926488"/>
<marker id="376926494"/>
<marker id="376926500"/>
<marker id="376926506"/>
<marker id="376926512"/>
<marker id="376926518"/>
<marker id="376926524"/>
<marker id="376926530"/>
<marker id="376926536"/>
<marker id="376926542"/>
<marker id="376926548"/>
<marker id="376926554"/>
<marker id="376926560"/>
<marker id="376926566"/>
<marker id="376926572"/>
<marker id="376926578"/>
<marker id="376926584"/>
<marker id="376926590"/>
<marker id="376926596"/>
<marker id="376926602"/>
<marker id="376926608"/>
<marker id="376926614"/>
<marker id="377004035"/>
<marker id="377004041"/>
<marker id="377004047"/>
<marker id="377004053"/>
<marker id="377004059"/>
<marker id="377004065"/>
<marker id="377004071"/>
<marker id="377004077"/>
<marker id="377004083"/>
<marker id="377004089"/>
<marker id="377004095"/>
<marker id="377004101"/>
<marker id="377004107"/>
<marker id="377004113"/>
<marker id="377004119"/>
<marker id="377004125"/>
<marker id="377004131"/>
<marker id="377004137"/>
<marker id="377004143"/>
<marker id="377004149"/>
<marker id="377004155"/>
<marker id="377004161"/>
<marker id="377004167"/>
<marker id="377004173"/>
<marker id="377012367"/>
<marker id="377012373"/>
<marker id="377012379"/>
<marker id="377012385"/>
<marker id="377012391"/>
<marker id="377012397"/>
<marker id="377012403"/>
<marker id="377012409"/>
<marker id="377012415"/>
<marker id="377012421"/>
<marker id="377012427"/>
<marker id="377012433"/>
<marker id="377012439"/>
<marker id="377012445"/>
<marker id="377012451"/>
<marker id="377012457"/>
<marker id="377012463"/>
<marker id="377012469"/>
<marker id="377073667"/>
<marker id="377073673"/>
<marker id="377073679"/>
<marker id="377073685"/>
<marker id="377073691"/>
<marker id="377073697"/>
<marker id="377073703"/>
<marker id="377073709"/>
<marker id="377073715"/>
<marker id="377073721"/>
<marker id="377073727"/>
<marker id="377073733"/>
<marker id="377073739"/>
<marker id="377073745"/>
<marker id="377073751"/>
<marker id="377073757"/>
<marker id="377073763"/>
<marker id="377073769"/>
<marker id="377073775"/>
<marker id="377073781"/>
<marker id="377073787"/>
<marker id="377073793"/>
<marker id="377073799"/>
<marker id="377073805"/>
<marker id="377073811"/>
<marker id="377135107"/>
<marker id="377135113"/>
<marker id="377135119"/>
<marker id="377135125"/>
<marker id="377135131"/>
<marker id="377135137"/>
<marker id="377135143"/>
<marker id="377135149"/>
<marker id="377135155"/>
<marker id="377135161"/>
<marker id="377135167"/>
<marker id="377135173"/>
<marker id="377135179"/>
<marker id="377135185"/>
<marker id="377135191"/>
<marker id="377135197"/>
<marker id="377135203"/>
<marker id="377135209"/>
<marker id="377135215"/>
<marker id="377135221"/>
<marker id="377135227"/>
<marker id="377135233"/>
<marker id="377135239"/>
<marker id="377135245"/>
<marker id="377204899"/>
<marker id="377204905"/>
<marker id="377204911"/>
<marker id="377204917"/>
<marker id="377204923"/>
<marker id="377204929"/>
<marker id="377204935"/>
<marker id="377204941"/>
<marker id="377204947"/>
<marker id="377204953"/>
<marker id="377204959"/>
<marker id="377204965"/>
<marker id="377204971"/>
<marker id="377204977"/>
<marker id="377204983"/>
<marker id="377204989"/>
<marker id="377266179"/>
<marker id="377266185"/>
<marker id="377266191"/>
<marker id="377266197"/>
<marker id="377266203"/>
<marker id="377266209"/>
<marker id="377266215"/>
<marker id="377266221"/>
<marker id="377266227"/>
<marker id="377266233"/>
<marker id="377266239"/>
<marker id="377266245"/>
<marker id="377266251"/>
<marker id="377266257"/>
<marker id="377266263"/>
<marker id="377266269"/>
<marker id="377290755"/>
<marker id="377290761"/>
<marker id="377290767"/>
<marker id="377290773"/>
<marker id="377290779"/>
<marker id="377290785"/>
<marker id="377290791"/>
<marker id="377290797"/>
<marker id="377290803"/>
<marker id="377290809"/>
<marker id="377307297"/>
<marker id="377307303"/>
<marker id="377307309"/>
<marker id="377307315"/>
<marker id="377307321"/>
<marker id="377307327"/>
<marker id="377307333"/>
<marker id="377307339"/>
<marker id="377307345"/>
<marker id="377307351"/>
<marker id="377336031"/>
<marker id="377336037"/>
<marker id="377336043"/>
<marker id="377336049"/>
<marker id="377336055"/>
<marker id="377336061"/>
<marker id="377336067"/>
<marker id="377336073"/>
<marker id="377336079"/>
<marker id="377336085"/>
<marker id="377336091"/>
<marker id="377336097"/>
<marker id="377336103"/>
<marker id="377336109"/>
<marker id="377336115"/>
<marker id="377336121"/>
<marker id="377336127"/>
<marker id="377336133"/>
<marker id="377336139"/>
<marker id="377336145"/>
<marker id="377336151"/>
<marker id="377336157"/>
<marker id="377336163"/>
<marker id="377336169"/>
<marker id="377336175"/>
<marker id="377360461"/>
<marker id="377360467"/>
<marker id="377360473"/>
<marker id="377360479"/>
<marker id="377360485"/>
<marker id="377360491"/>
<marker id="377360497"/>
<marker id="377360503"/>
<marker id="377360509"/>
<marker id="377360515"/>
<marker id="377368865"/>
<marker id="377368871"/>
<marker id="377368877"/>
<marker id="377368883"/>
<marker id="377368889"/>
<marker id="377368895"/>
<marker id="377368901"/>
<marker id="377368907"/>
<marker id="377368913"/>
<marker id="377368919"/>
<marker id="377422026"/>
<marker id="377422032"/>
<marker id="377422038"/>
<marker id="377422044"/>
<marker id="377422050"/>
<marker id="377422056"/>
<marker id="377422062"/>
<marker id="377422068"/>
<marker id="377422074"/>
<marker id="377422080"/>
<marker id="377438211"/>
<marker id="377438217"/>
<marker id="377438223"/>
<marker id="377438229"/>
<marker id="377438235"/>
<marker id="377438241"/>
<marker id="377438247"/>
<marker id="377438253"/>
<marker id="377438259"/>
<marker id="377462787"/>
<marker id="377462793"/>
<marker id="377462799"/>
<marker id="377462805"/>
<marker id="377462811"/>
<marker id="377462817"/>
<marker id="377462823"/>
<marker id="377462829"/>
<marker id="377462835"/>
<marker id="377462841"/>
<marker id="377462847"/>
<marker id="377462853"/>
<marker id="377462859"/>
<marker id="377462865"/>
<marker id="377462871"/>
<marker id="377462877"/>
<marker id="377462883"/>
<marker id="377462889"/>
<marker id="377462895"/>
<marker id="377462901"/>
<marker id="377462907"/>
<marker id="377462913"/>
<marker id="377462919"/>
<marker id="377462925"/>
<marker id="377462931"/>
<marker id="377470980"/>
<marker id="377470987"/>
<marker id="377470994"/>
<marker id="377471001"/>
<marker id="377479172"/>
<marker id="377479179"/>
<marker id="392228868"/>
<marker id="392228874"/>
<marker id="392228880"/>
<marker id="392228886"/>
<marker id="392228892"/>
<marker id="392228898"/>
<marker id="392228904"/>
<marker id="392228910"/>
<marker id="392228916"/>
<marker id="392228922"/>
<marker id="392290327"/>
<marker id="392290333"/>
<marker id="392290339"/>
<marker id="392290345"/>
<marker id="392290351"/>
<marker id="392290357"/>
<marker id="392290363"/>
<marker id="392290369"/>
<marker id="392290375"/>
<marker id="392290381"/>
<marker id="392360039"/>
<marker id="392360045"/>
<marker id="392360051"/>
<marker id="392360057"/>
<marker id="392360063"/>
<marker id="392360069"/>
<marker id="392360075"/>
<marker id="392360081"/>
<marker id="392360087"/>
<marker id="392360093"/>
<marker id="392421444"/>
<marker id="392421450"/>
<marker id="392421456"/>
<marker id="392421462"/>
<marker id="392421468"/>
<marker id="392421474"/>
<marker id="392421480"/>
<marker id="392421486"/>
<marker id="392421492"/>
<marker id="392421498"/>
<marker id="392491036"/>
<marker id="392491042"/>
<marker id="392491048"/>
<marker id="392491054"/>
<marker id="392491060"/>
<marker id="392491066"/>
<marker id="392491072"/>
<marker id="392491078"/>
<marker id="392491084"/>
<marker id="392491090"/>
<marker id="393261302"/>
<marker id="393261308"/>
<marker id="393261314"/>
<marker id="393261320"/>
<marker id="393261326"/>
<marker id="393261332"/>
<marker id="393261338"/>
<marker id="393261344"/>
<marker id="393261350"/>
<marker id="393261356"/>
<marker id="393261362"/>
<marker id="393261368"/>
<marker id="393261374"/>
<marker id="393261380"/>
<marker id="393261386"/>
<marker id="393261392"/>
<marker id="393261398"/>
<marker id="393261404"/>
<marker id="393261410"/>
<marker id="393261416"/>
<marker id="393261422"/>
<marker id="393261428"/>
<marker id="393261434"/>
<marker id="393261440"/>
<marker id="393269353"/>
<marker id="393269359"/>
<marker id="393269365"/>
<marker id="393269371"/>
<marker id="393269377"/>
<marker id="393269383"/>
<marker id="393269389"/>
<marker id="393269395"/>
<marker id="393289766"/>
<marker id="393289772"/>
<marker id="393289778"/>
<marker id="393289784"/>
<marker id="393289790"/>
<marker id="393289796"/>
<marker id="393289802"/>
<marker id="393289808"/>
<marker id="393289814"/>
<marker id="393289820"/>
<marker id="393297986"/>
<marker id="393297992"/>
<marker id="393297998"/>
<marker id="393298004"/>
<marker id="393298010"/>
<marker id="393298016"/>
<marker id="393298022"/>
<marker id="393298028"/>
<marker id="393298034"/>
<marker id="393298040"/>
<marker id="393322499"/>
<marker id="393322505"/>
<marker id="393322511"/>
<marker id="393322517"/>
<marker id="393322523"/>
<marker id="393322529"/>
<marker id="393330946"/>
<marker id="393330952"/>
<marker id="393330958"/>
<marker id="393330964"/>
<marker id="393330970"/>
<marker id="393330976"/>
<marker id="393330982"/>
<marker id="393330988"/>
<marker id="393330994"/>
<marker id="393331000"/>
<marker id="393331006"/>
<marker id="393331012"/>
<marker id="393331018"/>
<marker id="393331024"/>
<marker id="393331030"/>
<marker id="393331036"/>
<marker id="393331042"/>
<marker id="393331048"/>
<marker id="393331054"/>
<marker id="393331060"/>
<marker id="393331066"/>
<marker id="393331072"/>
<marker id="393331078"/>
<marker id="393331084"/>
<marker id="393334940"/>
<marker id="393334946"/>
<marker id="393334952"/>
<marker id="393334958"/>
<marker id="393334964"/>
<marker id="393334970"/>
<marker id="393334976"/>
<marker id="393334982"/>
<marker id="393351250"/>
<marker id="393351256"/>
<marker id="393351262"/>
<marker id="393351268"/>
<marker id="393351274"/>
<marker id="393351280"/>
<marker id="393351286"/>
<marker id="393351292"/>
<marker id="393351298"/>
<marker id="393351304"/>
<marker id="393359497"/>
<marker id="393359503"/>
<marker id="393359509"/>
<marker id="393359515"/>
<marker id="393359521"/>
<marker id="393359527"/>
<marker id="393359533"/>
<marker id="393359539"/>
<marker id="393359545"/>
<marker id="393359551"/>
<marker id="393367654"/>
<marker id="393367660"/>
<marker id="393367666"/>
<marker id="393367672"/>
<marker id="393367678"/>
<marker id="393367684"/>
<marker id="393367690"/>
<marker id="393367696"/>
<marker id="393367702"/>
<marker id="393367708"/>
<marker id="393392131"/>
<marker id="393392137"/>
<marker id="393392143"/>
<marker id="393392149"/>
<marker id="393392155"/>
<marker id="393392161"/>
<marker id="393392167"/>
<marker id="393392173"/>
<marker id="393392179"/>
<marker id="393392185"/>
<marker id="393396374"/>
<marker id="393396381"/>
<marker id="393396388"/>
<marker id="393408515"/>
<marker id="393408521"/>
<marker id="393408527"/>
<marker id="393408533"/>
<marker id="393408539"/>
<marker id="393408545"/>
<marker id="393408551"/>
<marker id="393408557"/>
<marker id="393408563"/>
<marker id="393408569"/>
<marker id="393412651"/>
<marker id="393412657"/>
<marker id="393412663"/>
<marker id="393412669"/>
<marker id="393412675"/>
<marker id="393412681"/>
<marker id="393412687"/>
<marker id="393412693"/>
<marker id="393412699"/>
<marker id="393412705"/>
<marker id="393420880"/>
<marker id="393420886"/>
<marker id="393420892"/>
<marker id="393420898"/>
<marker id="393420904"/>
<marker id="393420910"/>
<marker id="393420916"/>
<marker id="393420922"/>
<marker id="393420928"/>
<marker id="393420934"/>
<marker id="393429002"/>
<marker id="393429008"/>
<marker id="393429014"/>
<marker id="393429020"/>
<marker id="393429026"/>
<marker id="393429032"/>
<marker id="393429038"/>
<marker id="393429044"/>
<marker id="393429050"/>
<marker id="393429056"/>
<marker id="393453571"/>
<marker id="393453577"/>
<marker id="393453583"/>
<marker id="393453589"/>
<marker id="393453595"/>
<marker id="393453601"/>
<marker id="393453607"/>
<marker id="393453613"/>
<marker id="393453619"/>
<marker id="393461764"/>
<marker id="393461770"/>
<marker id="393461776"/>
<marker id="393461782"/>
<marker id="393461788"/>
<marker id="393461794"/>
<marker id="393461800"/>
<marker id="393461806"/>
<marker id="393461812"/>
<marker id="393461818"/>
<marker id="393469955"/>
<marker id="393469961"/>
<marker id="393469967"/>
<marker id="393469973"/>
<marker id="393469979"/>
<marker id="393469985"/>
<marker id="393469991"/>
<marker id="393469997"/>
<marker id="393470003"/>
<marker id="393470009"/>
<marker id="393523204"/>
<marker id="393523210"/>
<marker id="393523216"/>
<marker id="393523222"/>
<marker id="393523228"/>
<marker id="393523234"/>
<marker id="393523240"/>
<marker id="393523246"/>
<marker id="393523252"/>
<marker id="393523258"/>
<marker id="393531395"/>
<marker id="393531401"/>
<marker id="393531407"/>
<marker id="393531413"/>
<marker id="393531419"/>
<marker id="393531425"/>
<marker id="393539587"/>
<marker id="393539593"/>
<marker id="393539599"/>
<marker id="393539605"/>
<marker id="393539611"/>
<marker id="393539617"/>
<marker id="393539623"/>
<marker id="393539629"/>
<marker id="393539635"/>
<marker id="393543683"/>
<marker id="393543689"/>
<marker id="393543695"/>
<marker id="393543701"/>
<marker id="393543707"/>
<marker id="393543713"/>
<marker id="393543719"/>
<marker id="393543725"/>
<marker id="393543731"/>
<marker id="393543737"/>
<marker id="393551875"/>
<marker id="393551881"/>
<marker id="393551887"/>
<marker id="393551893"/>
<marker id="393551899"/>
<marker id="393551905"/>
<marker id="393551911"/>
<marker id="393551917"/>
<marker id="393551923"/>
<marker id="393551929"/>
<marker id="393584644"/>
<marker id="393584650"/>
<marker id="393584656"/>
<marker id="393584662"/>
<marker id="393584668"/>
<marker id="393584674"/>
<marker id="393584680"/>
<marker id="393613315"/>
<marker id="393613321"/>
<marker id="393613327"/>
<marker id="393613333"/>
<marker id="393613339"/>
<marker id="393613345"/>
<marker id="393613351"/>
<marker id="393613357"/>
<marker id="393613363"/>
<marker id="393613369"/>
<marker id="393674755"/>
<marker id="393674761"/>
<marker id="393674767"/>
<marker id="393674773"/>
<marker id="393674779"/>
<marker id="393674785"/>
<marker id="393674791"/>
<marker id="393674797"/>
<marker id="393674803"/>
<marker id="393674809"/>
<marker id="393682947"/>
<marker id="393682953"/>
<marker id="393682959"/>
<marker id="393682965"/>
<marker id="393682971"/>
<marker id="393682977"/>
<marker id="393682983"/>
<marker id="393682989"/>
<marker id="393682995"/>
<marker id="393683001"/>
<marker id="393744387"/>
<marker id="393744393"/>
<marker id="393744399"/>
<marker id="393744405"/>
<marker id="393744411"/>
<marker id="393744417"/>
<marker id="393744423"/>
<marker id="393744429"/>
<marker id="393744435"/>
<marker id="393744441"/>
<marker id="393924611"/>
<marker id="393924617"/>
<marker id="393924623"/>
<marker id="393924629"/>
<marker id="393924635"/>
<marker id="393924641"/>
<marker id="393924647"/>
<marker id="393924653"/>
<marker id="393924659"/>
<marker id="393924665"/>
<marker id="393932803"/>
<marker id="393932809"/>
<marker id="393932819"/>
<marker id="393932825"/>
<marker id="393932831"/>
<marker id="393932837"/>
<marker id="393932843"/>
<marker id="393932849"/>
<marker id="393932855"/>
<marker id="393932861"/>
<marker id="393994243"/>
<marker id="393994249"/>
<marker id="393994255"/>
<marker id="393994261"/>
<marker id="393994267"/>
<marker id="393994273"/>
<marker id="393994279"/>
<marker id="393994285"/>
<marker id="393994291"/>
<marker id="393994297"/>
<marker id="394055683"/>
<marker id="394055689"/>
<marker id="394055695"/>
<marker id="394055701"/>
<marker id="394055707"/>
<marker id="394055713"/>
<marker id="394055719"/>
<marker id="394055725"/>
<marker id="394055731"/>
<marker id="394055737"/>
<marker id="394063875"/>
<marker id="394063881"/>
<marker id="394063887"/>
<marker id="394063893"/>
<marker id="394063899"/>
<marker id="394063905"/>
<marker id="394063911"/>
<marker id="394063917"/>
<marker id="394063923"/>
<marker id="394063929"/>
<marker id="394117123"/>
<marker id="394117129"/>
<marker id="394117135"/>
<marker id="394117141"/>
<marker id="394117147"/>
<marker id="394117153"/>
<marker id="394117159"/>
<marker id="394117165"/>
<marker id="394117171"/>
<marker id="394125315"/>
<marker id="394125321"/>
<marker id="394125327"/>
<marker id="394125333"/>
<marker id="394125339"/>
<marker id="394125345"/>
<marker id="394125351"/>
<marker id="394125357"/>
<marker id="394125363"/>
<marker id="394125369"/>
<marker id="394186845"/>
<marker id="394186851"/>
<marker id="394186857"/>
<marker id="394186863"/>
<marker id="394186869"/>
<marker id="394186875"/>
<marker id="394186881"/>
<marker id="394186887"/>
<marker id="394186893"/>
<marker id="394186899"/>
<marker id="394194947"/>
<marker id="394194953"/>
<marker id="394194959"/>
<marker id="394194965"/>
<marker id="394194971"/>
<marker id="394194977"/>
<marker id="394194983"/>
<marker id="394194989"/>
<marker id="394194995"/>
<marker id="394195001"/>
<marker id="394248288"/>
<marker id="394248294"/>
<marker id="394248300"/>
<marker id="394248306"/>
<marker id="394248312"/>
<marker id="394248318"/>
<marker id="394248324"/>
<marker id="394248330"/>
<marker id="394248336"/>
<marker id="394248342"/>
<marker id="394256403"/>
<marker id="394256409"/>
<marker id="394256415"/>
<marker id="394256421"/>
<marker id="394256427"/>
<marker id="394256433"/>
<marker id="394256439"/>
<marker id="394256445"/>
<marker id="394256451"/>
<marker id="394256457"/>
<marker id="394383423"/>
<marker id="394383429"/>
<marker id="394383435"/>
<marker id="394383441"/>
<marker id="394383447"/>
<marker id="394383453"/>
<marker id="394383459"/>
<marker id="394383465"/>
<marker id="394383471"/>
<marker id="394383477"/>
<marker id="394383483"/>
<marker id="394383489"/>
<marker id="394383495"/>
<marker id="394383501"/>
<marker id="394383507"/>
<marker id="394383513"/>
<marker id="394436611"/>
<marker id="394436617"/>
<marker id="394436623"/>
<marker id="394436629"/>
<marker id="394436635"/>
<marker id="394436641"/>
<marker id="394436647"/>
<marker id="394436653"/>
<marker id="394436659"/>
<marker id="394436665"/>
<marker id="394461187"/>
<marker id="394461193"/>
<marker id="394461199"/>
<marker id="394461205"/>
<marker id="394461211"/>
<marker id="394461217"/>
<marker id="394498103"/>
<marker id="394498109"/>
<marker id="394498115"/>
<marker id="394498121"/>
<marker id="394498127"/>
<marker id="394498133"/>
<marker id="394498139"/>
<marker id="394498145"/>
<marker id="394498151"/>
<marker id="394498157"/>
<marker id="394506243"/>
<marker id="394506249"/>
<marker id="394506255"/>
<marker id="394506261"/>
<marker id="394506267"/>
<marker id="394506273"/>
<marker id="394506279"/>
<marker id="394506285"/>
<marker id="394506291"/>
<marker id="394506297"/>
<marker id="394559595"/>
<marker id="394559601"/>
<marker id="394559607"/>
<marker id="394559613"/>
<marker id="394559619"/>
<marker id="394559625"/>
<marker id="394559631"/>
<marker id="394559637"/>
<marker id="394559643"/>
<marker id="394559649"/>
<marker id="394567683"/>
<marker id="394567689"/>
<marker id="394567695"/>
<marker id="394567701"/>
<marker id="394567707"/>
<marker id="394567713"/>
<marker id="394567719"/>
<marker id="394567725"/>
<marker id="394567731"/>
<marker id="394567737"/>
<marker id="394600600"/>
<marker id="394600606"/>
<marker id="394600612"/>
<marker id="394600618"/>
<marker id="394600624"/>
<marker id="394600630"/>
<marker id="394600636"/>
<marker id="394600642"/>
<marker id="394600648"/>
<marker id="394600654"/>
<marker id="394600660"/>
<marker id="394600666"/>
<marker id="394600672"/>
<marker id="394600678"/>
<marker id="394600684"/>
<marker id="394600690"/>
<marker id="394600696"/>
<marker id="394600702"/>
<marker id="394600708"/>
<marker id="394600714"/>
<marker id="394600720"/>
<marker id="394600726"/>
<marker id="394600732"/>
<marker id="394600738"/>
<marker id="394604652"/>
<marker id="394604658"/>
<marker id="394604664"/>
<marker id="394604670"/>
<marker id="394604676"/>
<marker id="394604682"/>
<marker id="394604688"/>
<marker id="394604694"/>
<marker id="394604700"/>
<marker id="394604706"/>
<marker id="394604712"/>
<marker id="394604718"/>
<marker id="394604724"/>
<marker id="394604730"/>
<marker id="394604736"/>
<marker id="394604742"/>
<marker id="394604748"/>
<marker id="394604754"/>
<marker id="394604760"/>
<marker id="394604766"/>
<marker id="394604772"/>
<marker id="394604778"/>
<marker id="394604784"/>
<marker id="394612823"/>
<marker id="394612829"/>
<marker id="394612835"/>
<marker id="394612841"/>
<marker id="394612847"/>
<marker id="394612853"/>
<marker id="394612859"/>
<marker id="394612865"/>
<marker id="394612871"/>
<marker id="394612877"/>
<marker id="394612883"/>
<marker id="394612889"/>
<marker id="394612895"/>
<marker id="394612901"/>
<marker id="394620931"/>
<marker id="394620937"/>
<marker id="394620943"/>
<marker id="394620949"/>
<marker id="394620955"/>
<marker id="394620961"/>
<marker id="394620967"/>
<marker id="394620973"/>
<marker id="394620979"/>
<marker id="394620985"/>
<marker id="394629240"/>
<marker id="394629246"/>
<marker id="394629252"/>
<marker id="394629258"/>
<marker id="394629264"/>
<marker id="394629270"/>
<marker id="394629276"/>
<marker id="394629282"/>
<marker id="394629288"/>
<marker id="394629294"/>
<marker id="394670207"/>
<marker id="394670213"/>
<marker id="394670219"/>
<marker id="394670225"/>
<marker id="394670231"/>
<marker id="394670237"/>
<marker id="394670243"/>
<marker id="394670249"/>
<marker id="394670255"/>
<marker id="394670261"/>
<marker id="394670267"/>
<marker id="394670273"/>
<marker id="394670279"/>
<marker id="394670285"/>
<marker id="394670291"/>
<marker id="394670297"/>
<marker id="394670303"/>
<marker id="394670309"/>
<marker id="394670315"/>
<marker id="394670321"/>
<marker id="394670327"/>
<marker id="394670333"/>
<marker id="394670339"/>
<marker id="394670345"/>
<marker id="394674318"/>
<marker id="394674324"/>
<marker id="394674330"/>
<marker id="394674336"/>
<marker id="394674342"/>
<marker id="394674348"/>
<marker id="394674354"/>
<marker id="394674360"/>
<marker id="394674366"/>
<marker id="394674372"/>
<marker id="394674378"/>
<marker id="394674384"/>
<marker id="394674390"/>
<marker id="394674396"/>
<marker id="394674402"/>
<marker id="394674408"/>
<marker id="394674414"/>
<marker id="394674420"/>
<marker id="394674426"/>
<marker id="394674432"/>
<marker id="394674438"/>
<marker id="394674444"/>
<marker id="394674450"/>
<marker id="394678366"/>
<marker id="394678372"/>
<marker id="394678378"/>
<marker id="394678384"/>
<marker id="394678390"/>
<marker id="394678396"/>
<marker id="394678402"/>
<marker id="394678408"/>
<marker id="394678414"/>
<marker id="394678420"/>
<marker id="394678426"/>
<marker id="394678432"/>
<marker id="394678438"/>
<marker id="394678444"/>
<marker id="394678450"/>
<marker id="394698755"/>
<marker id="394698761"/>
<marker id="394698767"/>
<marker id="394698773"/>
<marker id="394698779"/>
<marker id="394698785"/>
<marker id="394698791"/>
<marker id="394698797"/>
<marker id="394698803"/>
<marker id="394698809"/>
<marker id="394731669"/>
<marker id="394731675"/>
<marker id="394731681"/>
<marker id="394731687"/>
<marker id="394731693"/>
<marker id="394731699"/>
<marker id="394731705"/>
<marker id="394731711"/>
<marker id="394731717"/>
<marker id="394731723"/>
<marker id="394731729"/>
<marker id="394731735"/>
<marker id="394731741"/>
<marker id="394731747"/>
<marker id="394731753"/>
<marker id="394731759"/>
<marker id="394731765"/>
<marker id="394731771"/>
<marker id="394731777"/>
<marker id="394731783"/>
<marker id="394731789"/>
<marker id="394731795"/>
<marker id="394731801"/>
<marker id="394731807"/>
<marker id="394760195"/>
<marker id="394760201"/>
<marker id="394760207"/>
<marker id="394760213"/>
<marker id="394760219"/>
<marker id="394760225"/>
<marker id="394760231"/>
<marker id="394760237"/>
<marker id="394760243"/>
<marker id="394768387"/>
<marker id="394768393"/>
<marker id="394768399"/>
<marker id="394768405"/>
<marker id="394768411"/>
<marker id="394768417"/>
<marker id="394768423"/>
<marker id="394768429"/>
<marker id="394768435"/>
<marker id="394768441"/>
<marker id="394776580"/>
<marker id="394776586"/>
<marker id="394776592"/>
<marker id="394776598"/>
<marker id="394776604"/>
<marker id="394776610"/>
<marker id="394793113"/>
<marker id="394793119"/>
<marker id="394793125"/>
<marker id="394793131"/>
<marker id="394793137"/>
<marker id="394793143"/>
<marker id="394793149"/>
<marker id="394793155"/>
<marker id="394793161"/>
<marker id="394793167"/>
<marker id="394793173"/>
<marker id="394793179"/>
<marker id="394793185"/>
<marker id="394793191"/>
<marker id="394793197"/>
<marker id="394793203"/>
<marker id="394793209"/>
<marker id="394793215"/>
<marker id="394793221"/>
<marker id="394793227"/>
<marker id="394793233"/>
<marker id="394793239"/>
<marker id="394793245"/>
<marker id="394793251"/>
<marker id="394801258"/>
<marker id="394801264"/>
<marker id="394801270"/>
<marker id="394801276"/>
<marker id="394801282"/>
<marker id="394801288"/>
<marker id="394801294"/>
<marker id="394801300"/>
<marker id="394801306"/>
<marker id="394801312"/>
<marker id="394801318"/>
<marker id="394801324"/>
<marker id="394801330"/>
<marker id="394801336"/>
<marker id="394801342"/>
<marker id="394801348"/>
<marker id="394838019"/>
<marker id="394838025"/>
<marker id="394838031"/>
<marker id="394838037"/>
<marker id="394838043"/>
<marker id="394838049"/>
<marker id="394838055"/>
<marker id="394838061"/>
<marker id="394838067"/>
<marker id="394838073"/>
<marker id="394854578"/>
<marker id="394854584"/>
<marker id="394854590"/>
<marker id="394854596"/>
<marker id="394854602"/>
<marker id="394854608"/>
<marker id="394854614"/>
<marker id="394854620"/>
<marker id="394854626"/>
<marker id="394854632"/>
<marker id="394854638"/>
<marker id="394854644"/>
<marker id="394854650"/>
<marker id="394854656"/>
<marker id="394854662"/>
<marker id="394854668"/>
<marker id="394854674"/>
<marker id="394854680"/>
<marker id="394854686"/>
<marker id="394854692"/>
<marker id="394854698"/>
<marker id="394854704"/>
<marker id="394854710"/>
<marker id="394903555"/>
<marker id="394903561"/>
<marker id="394903567"/>
<marker id="394903573"/>
<marker id="394903579"/>
<marker id="394903585"/>
<marker id="394903591"/>
<marker id="394903597"/>
<marker id="394903603"/>
<marker id="394903609"/>
<marker id="394911747"/>
<marker id="394911753"/>
<marker id="394911759"/>
<marker id="394911765"/>
<marker id="394911771"/>
<marker id="394911777"/>
<marker id="394911783"/>
<marker id="394911789"/>
<marker id="394911795"/>
<marker id="394911801"/>
<marker id="394973187"/>
<marker id="394973193"/>
<marker id="394973199"/>
<marker id="394973205"/>
<marker id="394973211"/>
<marker id="394973217"/>
<marker id="394973223"/>
<marker id="394973229"/>
<marker id="394973235"/>
<marker id="394973241"/>
<marker id="394981380"/>
<marker id="394981386"/>
<marker id="394981392"/>
<marker id="394981398"/>
<marker id="394981404"/>
<marker id="394981410"/>
<marker id="394981416"/>
<marker id="394981422"/>
<marker id="394981428"/>
<marker id="394981434"/>
<marker id="394985475"/>
<marker id="394985481"/>
<marker id="394985487"/>
<marker id="394985493"/>
<marker id="394985499"/>
<marker id="394985505"/>
<marker id="394985511"/>
<marker id="394985517"/>
<marker id="394985523"/>
<marker id="394985529"/>
<marker id="395116547"/>
<marker id="395116553"/>
<marker id="395116559"/>
<marker id="395116565"/>
<marker id="395116571"/>
<marker id="395116577"/>
<marker id="395116583"/>
<marker id="395116589"/>
<marker id="395116595"/>
<marker id="395116601"/>
<marker id="395247619"/>
<marker id="395247625"/>
<marker id="395247631"/>
<marker id="395247637"/>
<marker id="395247643"/>
<marker id="395247649"/>
<marker id="395247655"/>
<marker id="395247661"/>
<marker id="395247667"/>
<marker id="395247673"/>
<marker id="395644932"/>
<marker id="395644938"/>
<marker id="395644944"/>
<marker id="395644950"/>
<marker id="395644956"/>
<marker id="395644962"/>
<marker id="395644968"/>
<marker id="395644974"/>
<marker id="395644980"/>
<marker id="395644986"/>
<marker id="395714563"/>
<marker id="395714569"/>
<marker id="395714575"/>
<marker id="395714581"/>
<marker id="395714587"/>
<marker id="395714593"/>
<marker id="395780099"/>
<marker id="395780105"/>
<marker id="395780111"/>
<marker id="395780117"/>
<marker id="395780123"/>
<marker id="395780129"/>
<marker id="395780135"/>
<marker id="395780141"/>
<marker id="395780147"/>
<marker id="395780153"/>
<marker id="395841539"/>
<marker id="395841545"/>
<marker id="395841551"/>
<marker id="395841557"/>
<marker id="395841563"/>
<marker id="395841569"/>
<marker id="395841575"/>
<marker id="395841581"/>
<marker id="395841587"/>
<marker id="395841593"/>
<marker id="395902979"/>
<marker id="395902985"/>
<marker id="395902991"/>
<marker id="395902997"/>
<marker id="395903003"/>
<marker id="395903009"/>
<marker id="395903015"/>
<marker id="395903021"/>
<marker id="395903027"/>
<marker id="395903033"/>
<marker id="395911171"/>
<marker id="395911177"/>
<marker id="395911183"/>
<marker id="395911189"/>
<marker id="395911195"/>
<marker id="395911201"/>
<marker id="395911207"/>
<marker id="395911213"/>
<marker id="395911219"/>
<marker id="395911225"/>
<marker id="395972611"/>
<marker id="395972617"/>
<marker id="395972623"/>
<marker id="395972629"/>
<marker id="395972635"/>
<marker id="395972641"/>
<marker id="395972647"/>
<marker id="395972653"/>
<marker id="395972659"/>
<marker id="395972665"/>
<marker id="396034051"/>
<marker id="396034057"/>
<marker id="396034063"/>
<marker id="396034069"/>
<marker id="396034075"/>
<marker id="396034081"/>
<marker id="396034087"/>
<marker id="396034093"/>
<marker id="396034099"/>
<marker id="396034105"/>
<marker id="396042243"/>
<marker id="396042249"/>
<marker id="396042255"/>
<marker id="396042261"/>
<marker id="396042267"/>
<marker id="396042273"/>
<marker id="396042279"/>
<marker id="396042285"/>
<marker id="396042291"/>
<marker id="396042297"/>
<marker id="410046467"/>
<marker id="410046473"/>
<marker id="410046479"/>
<marker id="410046485"/>
<marker id="410046491"/>
<marker id="410046497"/>
<marker id="410046503"/>
<marker id="410046509"/>
<marker id="410046515"/>
<marker id="410046521"/>
<marker id="410054659"/>
<marker id="410054665"/>
<marker id="410054671"/>
<marker id="410054677"/>
<marker id="410054683"/>
<marker id="410054689"/>
<marker id="410054695"/>
<marker id="410054701"/>
<marker id="410054707"/>
<marker id="410054713"/>
<marker id="410107907"/>
<marker id="410107913"/>
<marker id="410107919"/>
<marker id="410107925"/>
<marker id="410107931"/>
<marker id="410107937"/>
<marker id="410107943"/>
<marker id="410107949"/>
<marker id="410107955"/>
<marker id="410107961"/>
<marker id="410116099"/>
<marker id="410116105"/>
<marker id="410116111"/>
<marker id="410116117"/>
<marker id="410116123"/>
<marker id="410116129"/>
<marker id="410116135"/>
<marker id="410116141"/>
<marker id="410116147"/>
<marker id="410116153"/>
<marker id="410128567"/>
<marker id="410128573"/>
<marker id="410128579"/>
<marker id="410128585"/>
<marker id="410128591"/>
<marker id="410128597"/>
<marker id="410128603"/>
<marker id="410128609"/>
<marker id="410128615"/>
<marker id="410128621"/>
<marker id="410148906"/>
<marker id="410148912"/>
<marker id="410148918"/>
<marker id="410148924"/>
<marker id="410148930"/>
<marker id="410157059"/>
<marker id="410157065"/>
<marker id="410157071"/>
<marker id="410157077"/>
<marker id="410157083"/>
<marker id="410157089"/>
<marker id="410157095"/>
<marker id="410157101"/>
<marker id="410169347"/>
<marker id="410169353"/>
<marker id="410169359"/>
<marker id="410169365"/>
<marker id="410169371"/>
<marker id="410169377"/>
<marker id="410169383"/>
<marker id="410169389"/>
<marker id="410169395"/>
<marker id="410169401"/>
<marker id="410177539"/>
<marker id="410177545"/>
<marker id="410177551"/>
<marker id="410177557"/>
<marker id="410177563"/>
<marker id="410177569"/>
<marker id="410177575"/>
<marker id="410177581"/>
<marker id="410177587"/>
<marker id="410177593"/>
<marker id="410198199"/>
<marker id="410198205"/>
<marker id="410198211"/>
<marker id="410198217"/>
<marker id="410198223"/>
<marker id="410198229"/>
<marker id="410198235"/>
<marker id="410198241"/>
<marker id="410198247"/>
<marker id="410198253"/>
<marker id="410210424"/>
<marker id="410210430"/>
<marker id="410210436"/>
<marker id="410210442"/>
<marker id="410210448"/>
<marker id="410210454"/>
<marker id="410210460"/>
<marker id="410210466"/>
<marker id="410210472"/>
<marker id="410210478"/>
<marker id="410226707"/>
<marker id="410226713"/>
<marker id="410226719"/>
<marker id="410226725"/>
<marker id="410226731"/>
<marker id="410226737"/>
<marker id="410226743"/>
<marker id="410226749"/>
<marker id="410226755"/>
<marker id="410238979"/>
<marker id="410238985"/>
<marker id="410238991"/>
<marker id="410238997"/>
<marker id="410239003"/>
<marker id="410239009"/>
<marker id="410239015"/>
<marker id="410239021"/>
<marker id="410239039"/>
<marker id="410239045"/>
<marker id="410259459"/>
<marker id="410259465"/>
<marker id="410259471"/>
<marker id="410259477"/>
<marker id="410259483"/>
<marker id="410259489"/>
<marker id="410259495"/>
<marker id="410259501"/>
<marker id="410259507"/>
<marker id="410259513"/>
<marker id="410267831"/>
<marker id="410267837"/>
<marker id="410267843"/>
<marker id="410267849"/>
<marker id="410267855"/>
<marker id="410267861"/>
<marker id="410267867"/>
<marker id="410267873"/>
<marker id="410267879"/>
<marker id="410267885"/>
<marker id="410276023"/>
<marker id="410276029"/>
<marker id="410276035"/>
<marker id="410276041"/>
<marker id="410276047"/>
<marker id="410276053"/>
<marker id="410276059"/>
<marker id="410276065"/>
<marker id="410276071"/>
<marker id="410276077"/>
<marker id="410280108"/>
<marker id="410280114"/>
<marker id="410280120"/>
<marker id="410280126"/>
<marker id="410280132"/>
<marker id="410280138"/>
<marker id="410280144"/>
<marker id="410280150"/>
<marker id="410280156"/>
<marker id="410280162"/>
<marker id="410284126"/>
<marker id="410284132"/>
<marker id="410284138"/>
<marker id="410284144"/>
<marker id="410284150"/>
<marker id="410284156"/>
<marker id="410284162"/>
<marker id="410284168"/>
<marker id="410292230"/>
<marker id="410292236"/>
<marker id="410292242"/>
<marker id="410292248"/>
<marker id="410292254"/>
<marker id="410292260"/>
<marker id="410292266"/>
<marker id="410292272"/>
<marker id="410292278"/>
<marker id="410292284"/>
<marker id="410296324"/>
<marker id="410296330"/>
<marker id="410296336"/>
<marker id="410296342"/>
<marker id="410296348"/>
<marker id="410300419"/>
<marker id="410300425"/>
<marker id="410300431"/>
<marker id="410300437"/>
<marker id="410300443"/>
<marker id="410300449"/>
<marker id="410300455"/>
<marker id="410300461"/>
<marker id="410300467"/>
<marker id="410308611"/>
<marker id="410308617"/>
<marker id="410308623"/>
<marker id="410308629"/>
<marker id="410308635"/>
<marker id="410308641"/>
<marker id="410308647"/>
<marker id="410308653"/>
<marker id="410308659"/>
<marker id="410308665"/>
<marker id="410320929"/>
<marker id="410320935"/>
<marker id="410320941"/>
<marker id="410320947"/>
<marker id="410320953"/>
<marker id="410320959"/>
<marker id="410320965"/>
<marker id="410320971"/>
<marker id="410320977"/>
<marker id="410320983"/>
<marker id="410337427"/>
<marker id="410337433"/>
<marker id="410337439"/>
<marker id="410337445"/>
<marker id="410337451"/>
<marker id="410337457"/>
<marker id="410337463"/>
<marker id="410337469"/>
<marker id="410337475"/>
<marker id="410337481"/>
<marker id="410345619"/>
<marker id="410345625"/>
<marker id="410345631"/>
<marker id="410345637"/>
<marker id="410345643"/>
<marker id="410345649"/>
<marker id="410345655"/>
<marker id="410345661"/>
<marker id="410345667"/>
<marker id="410345673"/>
<marker id="410353739"/>
<marker id="410353745"/>
<marker id="410353751"/>
<marker id="410353757"/>
<marker id="410353763"/>
<marker id="410353769"/>
<marker id="410353775"/>
<marker id="410353781"/>
<marker id="410353787"/>
<marker id="410361859"/>
<marker id="410361865"/>
<marker id="410361871"/>
<marker id="410361877"/>
<marker id="410361883"/>
<marker id="410361889"/>
<marker id="410362015"/>
<marker id="410362021"/>
<marker id="410362027"/>
<marker id="410362033"/>
<marker id="410362039"/>
<marker id="410390561"/>
<marker id="410390567"/>
<marker id="410390573"/>
<marker id="410390579"/>
<marker id="410390585"/>
<marker id="410390591"/>
<marker id="410390597"/>
<marker id="410390603"/>
<marker id="410390609"/>
<marker id="410390615"/>
<marker id="410407083"/>
<marker id="410407089"/>
<marker id="410407095"/>
<marker id="410407101"/>
<marker id="410407107"/>
<marker id="410407113"/>
<marker id="410407119"/>
<marker id="410407125"/>
<marker id="410407131"/>
<marker id="410407137"/>
<marker id="410415108"/>
<marker id="410415114"/>
<marker id="410415120"/>
<marker id="410415126"/>
<marker id="410415132"/>
<marker id="410415138"/>
<marker id="410423299"/>
<marker id="410423305"/>
<marker id="410423311"/>
<marker id="410423317"/>
<marker id="410423323"/>
<marker id="410423329"/>
<marker id="410423335"/>
<marker id="410423341"/>
<marker id="410423347"/>
<marker id="410468355"/>
<marker id="410468361"/>
<marker id="410468367"/>
<marker id="410468373"/>
<marker id="410468379"/>
<marker id="410468385"/>
<marker id="410468391"/>
<marker id="410468397"/>
<marker id="410476547"/>
<marker id="410476553"/>
<marker id="410476559"/>
<marker id="410476565"/>
<marker id="410485065"/>
<marker id="410485071"/>
<marker id="410485077"/>
<marker id="410485083"/>
<marker id="410485089"/>
<marker id="410485095"/>
<marker id="410485101"/>
<marker id="410485107"/>
<marker id="410521603"/>
<marker id="410521609"/>
<marker id="410521615"/>
<marker id="410521621"/>
<marker id="410521627"/>
<marker id="410521633"/>
<marker id="410521639"/>
<marker id="410521645"/>
<marker id="410521651"/>
<marker id="410521657"/>
<marker id="410529805"/>
<marker id="410529811"/>
<marker id="410529817"/>
<marker id="410529823"/>
<marker id="410537988"/>
<marker id="410537994"/>
<marker id="410538000"/>
<marker id="410538006"/>
<marker id="410538012"/>
<marker id="410538018"/>
<marker id="410538024"/>
<marker id="410538030"/>
<marker id="410538036"/>
<marker id="410538042"/>
<marker id="410591235"/>
<marker id="410591241"/>
<marker id="410591247"/>
<marker id="410591253"/>
<marker id="410591259"/>
<marker id="410591265"/>
<marker id="410591271"/>
<marker id="410591277"/>
<marker id="410591283"/>
<marker id="410591289"/>
<marker id="410607620"/>
<marker id="410607626"/>
<marker id="410607632"/>
<marker id="410607638"/>
<marker id="410607644"/>
<marker id="410607650"/>
<marker id="410607656"/>
<marker id="410607662"/>
<marker id="410607668"/>
<marker id="410607674"/>
<marker id="410652675"/>
<marker id="410652681"/>
<marker id="410652687"/>
<marker id="410652693"/>
<marker id="410652699"/>
<marker id="410652705"/>
<marker id="410652711"/>
<marker id="410652717"/>
<marker id="410652723"/>
<marker id="410652729"/>
<marker id="410660867"/>
<marker id="410660873"/>
<marker id="410660879"/>
<marker id="410660885"/>
<marker id="410660891"/>
<marker id="410660897"/>
<marker id="410660903"/>
<marker id="410660909"/>
<marker id="410660915"/>
<marker id="410660921"/>
<marker id="410669059"/>
<marker id="410669065"/>
<marker id="410669071"/>
<marker id="410669077"/>
<marker id="410669083"/>
<marker id="410669089"/>
<marker id="410669095"/>
<marker id="410669101"/>
<marker id="410669107"/>
<marker id="410669113"/>
<marker id="411045891"/>
<marker id="411045897"/>
<marker id="411045903"/>
<marker id="411045909"/>
<marker id="411045915"/>
<marker id="411045921"/>
</index>
